Workbook
Name DVCategory: Calc!$F$12:$F$17
Name DVCur: Calc!$I$12:$I$13
Name DVGrowth: Calc!$A$162:$U$162
Name DVLine: Calc!$J$12:$J$13
Name DVMonth: Calc!$D$12:$D$24
Name DVProduct: Calc!$H$12:$H$37
Name DVQuarter: Calc!$C$12:$C$16
Name DVRegion: Calc!$E$12:$E$17
Name DVSales: Calc!$G$12:$G$18
Name DVYear: Calc!$B$12:$B$16

Sheet Dashboard
A1: SALES ANALYTICS DASHBOARD 2022-2025 | Interactive Sales Performance | AB1: HELPERS
A2: YEAR | C2: QUARTER | E2: MONTH | G2: REGION | I2: CATEGORY | K2: SALESPERSON | M2: PRODUCT | P2: GROWTH % | Q2: CURRENCY | S2: TARGET | AB2: =IF(Q3="USD",1/18.5,1) -> 1 | AC2: =SUM(Calc!$B$42:$B$53)*(1+AB3/100)*AB2 -> 7862714.1 | AD2: Jan
A3: 2024 | C3: All | E3: All | G3: All | I3: All | K3: All | M3: All | P3: 60 | Q3: EGP | S3: ON | AB3: =P3 -> 60 | AC3: =IF(AB4=1,AC$2,"") -> 7862714.1 | AD3: Feb
A4: ="ACTIVE FILTERS YEAR = "&A3&" | QUARTER = "&C3&" | MONTH = "&E3&" | REGION = "&G3&" | CATEGORY = "&I3&" | SALESPERSON = "&K3&" | PRODUCT = "&M3&" | GROWTH = "&P3&"% | CURRENCY = "&Q3&" | TARGET = "&S3 -> ACTIVE FILTERS YEAR = 2024 | QUARTER = All | MONTH = All | REGION = All | CATEGORY = All | SALESPERSON = All | PRODUCT = All | GROWTH = 60% | CURRENCY = EGP | TARGET = ON | AB4: =IF(S3="ON",1,0) -> 1 | AC4: =IF(AB4=1,AC$2,"") -> 7862714.1 | AD4: Mar
A5: =IF(Q3="USD","TOTAL REVENUE (USD)","TOTAL REVENUE (EGP)") -> TOTAL REVENUE (EGP) | C5: ="TOTAL ORDERS" -> TOTAL ORDERS | E5: ="TOTAL UNITS" -> TOTAL UNITS | G5: =IF(Q3="USD","AVG ORDER VALUE (USD)","AVG ORDER VALUE (EGP)") -> AVG ORDER VALUE (EGP) | I5: =IF(Q3="USD","TOTAL PROFIT (USD)","TOTAL PROFIT (EGP)") -> TOTAL PROFIT (EGP) | K5: ="PROFIT MARGIN" -> PROFIT MARGIN | M5: =TEXT(NOW(),"HH:MM:SS")&" UPDATED" -> 04:47:34 UPDATED | Q5: GO TO CALC 👨‍🦯 | AC5: =IF(AB4=1,AC$2,"") -> 7862714.1 | AD5: Apr
A6: =SUM(Calc!$B$42:$B$53)*$AB$2 -> 4914196.3 | C6: =SUM(Calc!$C$42:$C$53) -> 180 | E6: =SUM(Calc!$D$42:$D$53) -> 3831 | G6: =IFERROR(SUM(Calc!$B$42:$B$53)/SUM(Calc!$C$42:$C$53),0)*$AB$2 -> 27301.091 | I6: =SUM(Calc!$F$42:$F$53)*$AB$2 -> 1867394.6 | K6: =IFERROR(SUM(Calc!$F$42:$F$53)/SUM(Calc!$B$42:$B$53),0) -> 0.38 | AC6: =IF(AB4=1,AC$2,"") -> 7862714.1 | AD6: May
A7: =IF(Q3="USD","TOTAL COST (USD)","TOTAL COST (EGP)") -> TOTAL COST (EGP) | C7: BEST MONTH | E7: AVG PROFIT / ORDER | G7: YOY GROWTH % | I7: COST RATIO % | K7: PEAK MONTH REVENUE | AC7: =IF(AB4=1,AC$2,"") -> 7862714.1 | AD7: Jun
A8: =SUM(Calc!$E$42:$E$53)*$AB$2 -> 3046801.7 | C8: =INDEX(Dashboard!$AD$2:$AD$13,MATCH(MAX(Calc!$I$42:$I$53),Calc!$I$42:$I$53,0)) -> Dec | E8: =IFERROR(SUM(Calc!$F$42:$F$53)/SUM(Calc!$C$42:$C$53),0)*$AB$2 -> 10374.415 | G8: =Calc!$F$166 -> 0.48732721 | I8: =IFERROR(SUM(Calc!$E$42:$E$53)/SUM(Calc!$B$42:$B$53),0) -> 0.62 | K8: =MAX(Calc!$I$42:$I$53) -> 931831.95 | AC8: =IF(AB4=1,AC$2,"") -> 7862714.1 | AD8: Jul
AC9: =IF(AB4=1,AC$2,"") -> 7862714.1 | AD9: Aug
A10: BEST CATEGORY | D10: TOP SALESPERSON | G10: PROJECTED REVENUE | P10: GoTo Data 👨‍🦯 | AC10: =IF(AB4=1,AC$2,"") -> 7862714.1 | AD10: Sep
A11: =INDEX(Calc!$A$75:$A$79,MATCH(MAX(Calc!$B$75:$B$79),Calc!$B$75:$B$79,0)) -> Electronics | D11: =INDEX(Calc!$A$84:$A$89,MATCH(MAX(Calc!$B$84:$B$89),Calc!$B$84:$B$89,0)) -> Mona Adel | G11: =(SUM(Calc!$B$42:$B$53))*(1+$P$3/100)*$AB$2 -> 7862714.1 | AC11: =IF(AB4=1,AC$2,"") -> 7862714.1 | AD11: Oct
AC12: =IF(AB4=1,AC$2,"") -> 7862714.1 | AD12: Nov
AC13: =IF(AB4=1,AC$2,"") -> 7862714.1 | AD13: Dec
AC14: =IF(AB4=1,AC$2,"") -> 7862714.1

Sheet Data
A1: Date | B1: Year | C1: Quarter | D1: MonthNum | E1: Month | F1: Region | G1: Category | H1: Product | I1: Salesperson | J1: Units | K1: Unit Price | L1: Revenue | M1: Cost | N1: Profit
A2: 44568.417 | B2: 2022 | C2: Q1 | D2: 1 | E2: Jan | F2: East | G2: Electronics | H2: Tablet | I2: Nour Ibrahim | J2: 29 | K2: 2127.12 | L2: 61686.48 | M2: 38245.62 | N2: 23440.86
A3: 44938.417 | B3: 2023 | C3: Q1 | D3: 1 | E3: Jan | F3: North | G3: Clothing | H3: Jacket | I3: Omar Mostafa | J3: 20 | K3: 417.14 | L3: 8342.8 | M3: 5172.54 | N3: 3170.26
A4: 45318.417 | B4: 2024 | C4: Q1 | D4: 1 | E4: Jan | F4: West | G4: Grocery | H4: Coffee | I4: Ahmed Hassan | J4: 52 | K4: 131.34 | L4: 6829.68 | M4: 4234.4 | N4: 2595.28
A5: 45659.417 | B5: 2025 | C5: Q1 | D5: 1 | E5: Jan | F5: Central | G5: Clothing | H5: Sneakers | I5: Ahmed Hassan | J5: 10 | K5: 181.21 | L5: 1812.1 | M5: 1123.5 | N5: 688.6
A6: 44595.417 | B6: 2022 | C6: Q1 | D6: 2 | E6: Feb | F6: Central | G6: Furniture | H6: Desk | I6: Khaled Youssef | J6: 5 | K6: 1320.3 | L6: 6601.5 | M6: 4092.93 | N6: 2508.57
A7: 44985.417 | B7: 2023 | C7: Q1 | D7: 2 | E7: Feb | F7: North | G7: Grocery | H7: Tea | I7: Ahmed Hassan | J7: 1 | K7: 74.41 | L7: 74.41 | M7: 46.13 | N7: 28.28
A8: 45330.417 | B8: 2024 | C8: Q1 | D8: 2 | E8: Feb | F8: North | G8: Grocery | H8: Sugar | I8: Mona Adel | J8: 14 | K8: 106.46 | L8: 1490.44 | M8: 924.07 | N8: 566.37
A9: 45696.417 | B9: 2025 | C9: Q1 | D9: 2 | E9: Feb | F9: Central | G9: Sports | H9: Dumbbell Set | I9: Khaled Youssef | J9: 17 | K9: 333.49 | L9: 5669.33 | M9: 3514.98 | N9: 2154.35
A10: 44634.417 | B10: 2022 | C10: Q1 | D10: 3 | E10: Mar | F10: East | G10: Furniture | H10: Bookshelf | I10: Ahmed Hassan | J10: 9 | K10: 1612.3 | L10: 14510.7 | M10: 8996.63 | N10: 5514.07
A11: 45002.417 | B11: 2023 | C11: Q1 | D11: 3 | E11: Mar | F11: East | G11: Sports | H11: Yoga Mat | I11: Mona Adel | J11: 22 | K11: 384.75 | L11: 8464.5 | M11: 5247.99 | N11: 3216.51
A12: 45360.417 | B12: 2024 | C12: Q1 | D12: 3 | E12: Mar | F12: East | G12: Grocery | H12: Sugar | I12: Mona Adel | J12: 9 | K12: 79.3 | L12: 713.7 | M12: 442.49 | N12: 271.21
A13: 45736.417 | B13: 2025 | C13: Q1 | D13: 3 | E13: Mar | F13: West | G13: Furniture | H13: Sofa | I13: Omar Mostafa | J13: 24 | K13: 1329.6 | L13: 31910.4 | M13: 19784.45 | N13: 12125.95
... A721: 45994.417 | B721: 2025 | C721: Q4 | D721: 12 | E721: Dec | F721: South | G721: Clothing | H721: T-Shirt | I721: Khaled Youssef | J721: 24 | K721: 168.55 | L721: 4045.2 | M721: 2508.02 | N721: 1537.18

Sheet Calc
A1: CALC ENGINE - DYNAMIC FORMULA LAYER
A2: Read-only formula layer driving the Dashboard. v2: quarter/month/product filters, year + product + top-10 + region x category matrix + KPI helpers.
A4: 1 | CURRENT SELECTIONS (read from the Dashboard controls) | L4: Go To
A5: FIELD | B5: YEAR | C5: QUARTER | D5: MONTH | E5: REGION | F5: CATEGORY | G5: SALESPERSON | H5: PRODUCT | I5: GROWTH % | J5: CURRENCY | K5: TARGET | L5: Dashboard 👨‍🦯
A6: ENGINE | B6: =Dashboard!A3 -> 2024 | C6: =Dashboard!C3 -> All | D6: =Dashboard!E3 -> All | E6: =Dashboard!G3 -> All | F6: =Dashboard!I3 -> All | G6: =Dashboard!K3 -> All | H6: =Dashboard!M3 -> All | I6: =Dashboard!P3 -> 60 | J6: =Dashboard!Q3 -> EGP | K6: =Dashboard!S3 -> ON
A7: READABLE | B7: =B6 -> 2024 | C7: =C6 -> All | D7: =D6 -> All | E7: =E6 -> All | F7: =F6 -> All | G7: =G6 -> All | H7: =H6 -> All | I7: =I6 -> 60 | ... K7: =K6 -> ON | L7: GoTo Data 👨‍🦯
A10: 2 | DROPDOWN LIST SOURCES - feed the in-cell dropdowns on the Dashboard
B11: YEAR | C11: QUARTER | D11: MONTH | E11: REGION | F11: CATEGORY | G11: SALESPERSON | H11: PRODUCT | I11: CURRENCY | J11: TARGET
B12: All | C12: All | D12: All | E12: All | F12: All | G12: All | H12: All | I12: EGP | J12: ON
B13: 2022 | C13: Q1 | D13: Jan | E13: North | F13: Grocery | G13: Ahmed Hassan | H13: Bookshelf | I13: USD | J13: OFF
B14: 2023 | C14: Q2 | D14: Feb | E14: South | F14: Furniture | G14: Sara Ali | H14: Coffee
B15: 2024 | C15: Q3 | D15: Mar | E15: East | F15: Clothing | G15: Omar Mostafa | H15: Cooking Oil
B16: 2025 | C16: Q4 | D16: Apr | E16: West | F16: Sports | G16: Nour Ibrahim | H16: Desk
D17: May | E17: Central | F17: Electronics | G17: Khaled Youssef | H17: Dumbbell Set
D18: Jun | G18: Mona Adel | H18: Floor Lamp
D19: Jul | H19: Football
D20: Aug | H20: Headset
D21: Sep | H21: Jacket
D22: Oct | H22: Jeans
D23: Nov | H23: Laptop
D24: Dec | H24: Monitor
H25: Office Chair
H26: Rice
H27: Smartphone
H28: Sneakers
H29: Sofa
H30: Sugar
H31: Sweater
H32: T-Shirt
H33: Tablet
H34: Tea
H35: Tennis Racket
H36: Training Jersey
H37: Yoga Mat
A40: 3 | MONTHLY TOTALS (Revenue / Orders / Units / Cost / Profit)
A41: Month | B41: Revenue | C41: Orders | D41: Units | E41: Cost | F41: Profit | G41: SHARE % | H41: YoY % | I41: Revenue USD | J41: Profit USD
A42: 1 | B42: =SUMPRODUCT((SalesData[MonthNum]=$A$42)*(($B$6="All")+(SalesData[Year]=$B$6))*(($C$6="All")+(SalesData[Quarter]=$C$6))*(($E$6="All")+(SalesData[Region]=$E$6))*(($F$6="All")+(SalesData[Category]=$F$6))*(($G$6="All")+(SalesData[Salesperson]=$G$6))*(($H$6="All")+(SalesData[Product]=$H$6))*SalesData[Revenue]) -> 798620.35 | C42: =SUMPRODUCT((SalesData[MonthNum]=$A$42)*(($B$6="All")+(SalesData[Year]=$B$6))*(($C$6="All")+(SalesData[Quarter]=$C$6))*(($E$6="All")+(SalesData[Region]=$E$6))*(($F$6="All")+(SalesData[Category]=$F$6))*(($G$6="All")+(SalesData[Salesperson]=$G$6))*(($H$6="All")+(SalesData[Product]=$H$6))*((SalesData[Units]<>0))) -> 15 | D42: =SUMPRODUCT((SalesData[MonthNum]=$A$42)*(($B$6="All")+(SalesData[Year]=$B$6))*(($C$6="All")+(SalesData[Quarter]=$C$6))*(($E$6="All")+(SalesData[Region]=$E$6))*(($F$6="All")+(SalesData[Category]=$F$6))*(($G$6="All")+(SalesData[Salesperson]=$G$6))*(($H$6="All")+(SalesData[Product]=$H$6))*SalesData[Units]) -> 463 | E42: =SUMPRODUCT((SalesData[MonthNum]=$A$42)*(($B$6="All")+(SalesData[Year]=$B$6))*(($C$6="All")+(SalesData[Quarter]=$C$6))*(($E$6="All")+(SalesData[Region]=$E$6))*(($F$6="All")+(SalesData[Category]=$F$6))*(($G$6="All")+(SalesData[Salesperson]=$G$6))*(($H$6="All")+(SalesData[Product]=$H$6))*SalesData[Cost]) -> 495144.61 | F42: =SUMPRODUCT((SalesData[MonthNum]=$A$42)*(($B$6="All")+(SalesData[Year]=$B$6))*(($C$6="All")+(SalesData[Quarter]=$C$6))*(($E$6="All")+(SalesData[Region]=$E$6))*(($F$6="All")+(SalesData[Category]=$F$6))*(($G$6="All")+(SalesData[Salesperson]=$G$6))*(($H$6="All")+(SalesData[Product]=$H$6))*SalesData[Profit]) -> 303475.74 | G42: =IFERROR(B42/SUM($B$42:$B$53),0) -> 0.16251291 | H42: =IF(NOT(ISNUMBER($B$6)),"n/a",IF($B$6<=2022,"n/a",IFERROR((B42-SUMPRODUCT((SalesData[MonthNum]=$A$42)*(SalesData[Year]=$B$6-1)*(($C$6="All")+(SalesData[Quarter]=$C$6))*(($D$6="All")+(SalesData[Month]=$D$6))*(($E$6="All")+(SalesData[Region]=$E$6))*(($F$6="All")+(SalesData[Category]=$F$6))*(($G$6="All")+(SalesData[Salesperson]=$G$6))*(($H$6="All")+(SalesData[Product]=$H$6))*SalesData[Revenue]))/SUMPRODUCT((SalesData[MonthNum]=$A$42)*(SalesData[Year]=$B$6-1)*(($C$6="All")+(SalesData[Quarter]=$C$6))*(($D$6="All")+(SalesData[Month]=$D$6))*(($E$6="All")+(SalesData[Region]=$E$6))*(($F$6="All")+(SalesData[Category]=$F$6))*(($G$6="All")+(SalesData[Salesperson]=$G$6))*(($H$6="All")+(SalesData[Product]=$H$6))*SalesData[Revenue]),"n/a"))) -> 0.58285342 | I42: =B42*Dashboard!$AB$2 -> 798620.35 | J42: =F42*Dashboard!$AB$2 -> 303475.74
A43: 2 | B43: =SUMPRODUCT((SalesData[MonthNum]=$A$43)*(($B$6="All")+(SalesData[Year]=$B$6))*(($C$6="All")+(SalesData[Quarter]=$C$6))*(($E$6="All")+(SalesData[Region]=$E$6))*(($F$6="All")+(SalesData[Category]=$F$6))*(($G$6="All")+(SalesData[Salesperson]=$G$6))*(($H$6="All")+(SalesData[Product]=$H$6))*SalesData[Revenue]) -> 384847.49 | C43: =SUMPRODUCT((SalesData[MonthNum]=$A$43)*(($B$6="All")+(SalesData[Year]=$B$6))*(($C$6="All")+(SalesData[Quarter]=$C$6))*(($E$6="All")+(SalesData[Region]=$E$6))*(($F$6="All")+(SalesData[Category]=$F$6))*(($G$6="All")+(SalesData[Salesperson]=$G$6))*(($H$6="All")+(SalesData[Product]=$H$6))*((SalesData[Units]<>0))) -> 15 | D43: =SUMPRODUCT((SalesData[MonthNum]=$A$43)*(($B$6="All")+(SalesData[Year]=$B$6))*(($C$6="All")+(SalesData[Quarter]=$C$6))*(($E$6="All")+(SalesData[Region]=$E$6))*(($F$6="All")+(SalesData[Category]=$F$6))*(($G$6="All")+(SalesData[Salesperson]=$G$6))*(($H$6="All")+(SalesData[Product]=$H$6))*SalesData[Units]) -> 197 | E43: =SUMPRODUCT((SalesData[MonthNum]=$A$43)*(($B$6="All")+(SalesData[Year]=$B$6))*(($C$6="All")+(SalesData[Quarter]=$C$6))*(($E$6="All")+(SalesData[Region]=$E$6))*(($F$6="All")+(SalesData[Category]=$F$6))*(($G$6="All")+(SalesData[Salesperson]=$G$6))*(($H$6="All")+(SalesData[Product]=$H$6))*SalesData[Cost]) -> 238605.45 | F43: =SUMPRODUCT((SalesData[MonthNum]=$A$43)*(($B$6="All")+(SalesData[Year]=$B$6))*(($C$6="All")+(SalesData[Quarter]=$C$6))*(($E$6="All")+(SalesData[Region]=$E$6))*(($F$6="All")+(SalesData[Category]=$F$6))*(($G$6="All")+(SalesData[Salesperson]=$G$6))*(($H$6="All")+(SalesData[Product]=$H$6))*SalesData[Profit]) -> 146242.04 | G43: =IFERROR(B43/SUM($B$42:$B$53),0) -> 0.078313414 | H43: =IF(NOT(ISNUMBER($B$6)),"n/a",IF($B$6<=2022,"n/a",IFERROR((B43-SUMPRODUCT((SalesData[MonthNum]=$A$43)*(SalesData[Year]=$B$6-1)*(($C$6="All")+(SalesData[Quarter]=$C$6))*(($D$6="All")+(SalesData[Month]=$D$6))*(($E$6="All")+(SalesData[Region]=$E$6))*(($F$6="All")+(SalesData[Category]=$F$6))*(($G$6="All")+(SalesData[Salesperson]=$G$6))*(($H$6="All")+(SalesData[Product]=$H$6))*SalesData[Revenue]))/SUMPRODUCT((SalesData[MonthNum]=$A$43)*(SalesData[Year]=$B$6-1)*(($C$6="All")+(SalesData[Quarter]=$C$6))*(($D$6="All")+(SalesData[Month]=$D$6))*(($E$6="All")+(SalesData[Region]=$E$6))*(($F$6="All")+(SalesData[Category]=$F$6))*(($G$6="All")+(SalesData[Salesperson]=$G$6))*(($H$6="All")+(SalesData[Product]=$H$6))*SalesData[Revenue]),"n/a"))) -> 5.3928707 | I43: =B43*Dashboard!$AB$2 -> 384847.49 | J43: =F43*Dashboard!$AB$2 -> 146242.04
A44: 3 | B44: =SUMPRODUCT((SalesData[MonthNum]=$A$44)*(($B$6="All")+(SalesData[Year]=$B$6))*(($C$6="All")+(SalesData[Quarter]=$C$6))*(($E$6="All")+(SalesData[Region]=$E$6))*(($F$6="All")+(SalesData[Category]=$F$6))*(($G$6="All")+(SalesData[Salesperson]=$G$6))*(($H$6="All")+(SalesData[Product]=$H$6))*SalesData[Revenue]) -> 75262.54 | C44: =SUMPRODUCT((SalesData[MonthNum]=$A$44)*(($B$6="All")+(SalesData[Year]=$B$6))*(($C$6="All")+(SalesData[Quarter]=$C$6))*(($E$6="All")+(SalesData[Region]=$E$6))*(($F$6="All")+(SalesData[Category]=$F$6))*(($G$6="All")+(SalesData[Salesperson]=$G$6))*(($H$6="All")+(SalesData[Product]=$H$6))*((SalesData[Units]<>0))) -> 15 | D44: =SUMPRODUCT((SalesData[MonthNum]=$A$44)*(($B$6="All")+(SalesData[Year]=$B$6))*(($C$6="All")+(SalesData[Quarter]=$C$6))*(($E$6="All")+(SalesData[Region]=$E$6))*(($F$6="All")+(SalesData[Category]=$F$6))*(($G$6="All")+(SalesData[Salesperson]=$G$6))*(($H$6="All")+(SalesData[Product]=$H$6))*SalesData[Units]) -> 206 | E44: =SUMPRODUCT((SalesData[MonthNum]=$A$44)*(($B$6="All")+(SalesData[Year]=$B$6))*(($C$6="All")+(SalesData[Quarter]=$C$6))*(($E$6="All")+(SalesData[Region]=$E$6))*(($F$6="All")+(SalesData[Category]=$F$6))*(($G$6="All")+(SalesData[Salesperson]=$G$6))*(($H$6="All")+(SalesData[Product]=$H$6))*SalesData[Cost]) -> 46662.78 | F44: =SUMPRODUCT((SalesData[MonthNum]=$A$44)*(($B$6="All")+(SalesData[Year]=$B$6))*(($C$6="All")+(SalesData[Quarter]=$C$6))*(($E$6="All")+(SalesData[Region]=$E$6))*(($F$6="All")+(SalesData[Category]=$F$6))*(($G$6="All")+(SalesData[Salesperson]=$G$6))*(($H$6="All")+(SalesData[Product]=$H$6))*SalesData[Profit]) -> 28599.76 | G44: =IFERROR(B44/SUM($B$42:$B$53),0) -> 0.01531533 | H44: =IF(NOT(ISNUMBER($B$6)),"n/a",IF($B$6<=2022,"n/a",IFERROR((B44-SUMPRODUCT((SalesData[MonthNum]=$A$44)*(SalesData[Year]=$B$6-1)*(($C$6="All")+(SalesData[Quarter]=$C$6))*(($D$6="All")+(SalesData[Month]=$D$6))*(($E$6="All")+(SalesData[Region]=$E$6))*(($F$6="All")+(SalesData[Category]=$F$6))*(($G$6="All")+(SalesData[Salesperson]=$G$6))*(($H$6="All")+(SalesData[Product]=$H$6))*SalesData[Revenue]))/SUMPRODUCT((SalesData[MonthNum]=$A$44)*(SalesData[Year]=$B$6-1)*(($C$6="All")+(SalesData[Quarter]=$C$6))*(($D$6="All")+(SalesData[Month]=$D$6))*(($E$6="All")+(SalesData[Region]=$E$6))*(($F$6="All")+(SalesData[Category]=$F$6))*(($G$6="All")+(SalesData[Salesperson]=$G$6))*(($H$6="All")+(SalesData[Product]=$H$6))*SalesData[Revenue]),"n/a"))) -> 0.3987596 | I44: =B44*Dashboard!$AB$2 -> 75262.54 | J44: =F44*Dashboard!$AB$2 -> 28599.76
A45: 4 | B45: =SUMPRODUCT((SalesData[MonthNum]=$A$45)*(($B$6="All")+(SalesData[Year]=$B$6))*(($C$6="All")+(SalesData[Quarter]=$C$6))*(($E$6="All")+(SalesData[Region]=$E$6))*(($F$6="All")+(SalesData[Category]=$F$6))*(($G$6="All")+(SalesData[Salesperson]=$G$6))*(($H$6="All")+(SalesData[Product]=$H$6))*SalesData[Revenue]) -> 431756.67 | C45: =SUMPRODUCT((SalesData[MonthNum]=$A$45)*(($B$6="All")+(SalesData[Year]=$B$6))*(($C$6="All")+(SalesData[Quarter]=$C$6))*(($E$6="All")+(SalesData[Region]=$E$6))*(($F$6="All")+(SalesData[Category]=$F$6))*(($G$6="All")+(SalesData[Salesperson]=$G$6))*(($H$6="All")+(SalesData[Product]=$H$6))*((SalesData[Units]<>0))) -> 15 | D45: =SUMPRODUCT((SalesData[MonthNum]=$A$45)*(($B$6="All")+(SalesData[Year]=$B$6))*(($C$6="All")+(SalesData[Quarter]=$C$6))*(($E$6="All")+(SalesData[Region]=$E$6))*(($F$6="All")+(SalesData[Category]=$F$6))*(($G$6="All")+(SalesData[Salesperson]=$G$6))*(($H$6="All")+(SalesData[Product]=$H$6))*SalesData[Units]) -> 262 | E45: =SUMPRODUCT((SalesData[MonthNum]=$A$45)*(($B$6="All")+(SalesData[Year]=$B$6))*(($C$6="All")+(SalesData[Quarter]=$C$6))*(($E$6="All")+(SalesData[Region]=$E$6))*(($F$6="All")+(SalesData[Category]=$F$6))*(($G$6="All")+(SalesData[Salesperson]=$G$6))*(($H$6="All")+(SalesData[Product]=$H$6))*SalesData[Cost]) -> 267689.12 | F45: =SUMPRODUCT((SalesData[MonthNum]=$A$45)*(($B$6="All")+(SalesData[Year]=$B$6))*(($C$6="All")+(SalesData[Quarter]=$C$6))*(($E$6="All")+(SalesData[Region]=$E$6))*(($F$6="All")+(SalesData[Category]=$F$6))*(($G$6="All")+(SalesData[Salesperson]=$G$6))*(($H$6="All")+(SalesData[Product]=$H$6))*SalesData[Profit]) -> 164067.55 | G45: =IFERROR(B45/SUM($B$42:$B$53),0) -> 0.08785906 | H45: =IF(NOT(ISNUMBER($B$6)),"n/a",IF($B$6<=2022,"n/a",IFERROR((B45-SUMPRODUCT((SalesData[MonthNum]=$A$45)*(SalesData[Year]=$B$6-1)*(($C$6="All")+(SalesData[Quarter]=$C$6))*(($D$6="All")+(SalesData[Month]=$D$6))*(($E$6="All")+(SalesData[Region]=$E$6))*(($F$6="All")+(SalesData[Category]=$F$6))*(($G$6="All")+(SalesData[Salesperson]=$G$6))*(($H$6="All")+(SalesData[Product]=$H$6))*SalesData[Revenue]))/SUMPRODUCT((SalesData[MonthNum]=$A$45)*(SalesData[Year]=$B$6-1)*(($C$6="All")+(SalesData[Quarter]=$C$6))*(($D$6="All")+(SalesData[Month]=$D$6))*(($E$6="All")+(SalesData[Region]=$E$6))*(($F$6="All")+(SalesData[Category]=$F$6))*(($G$6="All")+(SalesData[Salesperson]=$G$6))*(($H$6="All")+(SalesData[Product]=$H$6))*SalesData[Revenue]),"n/a"))) -> -0.11975082 | I45: =B45*Dashboard!$AB$2 -> 431756.67 | J45: =F45*Dashboard!$AB$2 -> 164067.55
A46: 5 | B46: =SUMPRODUCT((SalesData[MonthNum]=$A$46)*(($B$6="All")+(SalesData[Year]=$B$6))*(($C$6="All")+(SalesData[Quarter]=$C$6))*(($E$6="All")+(SalesData[Region]=$E$6))*(($F$6="All")+(SalesData[Category]=$F$6))*(($G$6="All")+(SalesData[Salesperson]=$G$6))*(($H$6="All")+(SalesData[Product]=$H$6))*SalesData[Revenue]) -> 208424.18 | C46: =SUMPRODUCT((SalesData[MonthNum]=$A$46)*(($B$6="All")+(SalesData[Year]=$B$6))*(($C$6="All")+(SalesData[Quarter]=$C$6))*(($E$6="All")+(SalesData[Region]=$E$6))*(($F$6="All")+(SalesData[Category]=$F$6))*(($G$6="All")+(SalesData[Salesperson]=$G$6))*(($H$6="All")+(SalesData[Product]=$H$6))*((SalesData[Units]<>0))) -> 15 | D46: =SUMPRODUCT((SalesData[MonthNum]=$A$46)*(($B$6="All")+(SalesData[Year]=$B$6))*(($C$6="All")+(SalesData[Quarter]=$C$6))*(($E$6="All")+(SalesData[Region]=$E$6))*(($F$6="All")+(SalesData[Category]=$F$6))*(($G$6="All")+(SalesData[Salesperson]=$G$6))*(($H$6="All")+(SalesData[Product]=$H$6))*SalesData[Units]) -> 268 | E46: =SUMPRODUCT((SalesData[MonthNum]=$A$46)*(($B$6="All")+(SalesData[Year]=$B$6))*(($C$6="All")+(SalesData[Quarter]=$C$6))*(($E$6="All")+(SalesData[Region]=$E$6))*(($F$6="All")+(SalesData[Category]=$F$6))*(($G$6="All")+(SalesData[Salesperson]=$G$6))*(($H$6="All")+(SalesData[Product]=$H$6))*SalesData[Cost]) -> 129222.99 | F46: =SUMPRODUCT((SalesData[MonthNum]=$A$46)*(($B$6="All")+(SalesData[Year]=$B$6))*(($C$6="All")+(SalesData[Quarter]=$C$6))*(($E$6="All")+(SalesData[Region]=$E$6))*(($F$6="All")+(SalesData[Category]=$F$6))*(($G$6="All")+(SalesData[Salesperson]=$G$6))*(($H$6="All")+(SalesData[Product]=$H$6))*SalesData[Profit]) -> 79201.19 | G46: =IFERROR(B46/SUM($B$42:$B$53),0) -> 0.042412669 | H46: =IF(NOT(ISNUMBER($B$6)),"n/a",IF($B$6<=2022,"n/a",IFERROR((B46-SUMPRODUCT((SalesData[MonthNum]=$A$46)*(SalesData[Year]=$B$6-1)*(($C$6="All")+(SalesData[Quarter]=$C$6))*(($D$6="All")+(SalesData[Month]=$D$6))*(($E$6="All")+(SalesData[Region]=$E$6))*(($F$6="All")+(SalesData[Category]=$F$6))*(($G$6="All")+(SalesData[Salesperson]=$G$6))*(($H$6="All")+(SalesData[Product]=$H$6))*SalesData[Revenue]))/SUMPRODUCT((SalesData[MonthNum]=$A$46)*(SalesData[Year]=$B$6-1)*(($C$6="All")+(SalesData[Quarter]=$C$6))*(($D$6="All")+(SalesData[Month]=$D$6))*(($E$6="All")+(SalesData[Region]=$E$6))*(($F$6="All")+(SalesData[Category]=$F$6))*(($G$6="All")+(SalesData[Salesperson]=$G$6))*(($H$6="All")+(SalesData[Product]=$H$6))*SalesData[Revenue]),"n/a"))) -> -0.052679198 | I46: =B46*Dashboard!$AB$2 -> 208424.18 | J46: =F46*Dashboard!$AB$2 -> 79201.19
A47: 6 | B47: =SUMPRODUCT((SalesData[MonthNum]=$A$47)*(($B$6="All")+(SalesData[Year]=$B$6))*(($C$6="All")+(SalesData[Quarter]=$C$6))*(($E$6="All")+(SalesData[Region]=$E$6))*(($F$6="All")+(SalesData[Category]=$F$6))*(($G$6="All")+(SalesData[Salesperson]=$G$6))*(($H$6="All")+(SalesData[Product]=$H$6))*SalesData[Revenue]) -> 270459.49 | C47: =SUMPRODUCT((SalesData[MonthNum]=$A$47)*(($B$6="All")+(SalesData[Year]=$B$6))*(($C$6="All")+(SalesData[Quarter]=$C$6))*(($E$6="All")+(SalesData[Region]=$E$6))*(($F$6="All")+(SalesData[Category]=$F$6))*(($G$6="All")+(SalesData[Salesperson]=$G$6))*(($H$6="All")+(SalesData[Product]=$H$6))*((SalesData[Units]<>0))) -> 15 | D47: =SUMPRODUCT((SalesData[MonthNum]=$A$47)*(($B$6="All")+(SalesData[Year]=$B$6))*(($C$6="All")+(SalesData[Quarter]=$C$6))*(($E$6="All")+(SalesData[Region]=$E$6))*(($F$6="All")+(SalesData[Category]=$F$6))*(($G$6="All")+(SalesData[Salesperson]=$G$6))*(($H$6="All")+(SalesData[Product]=$H$6))*SalesData[Units]) -> 280 | E47: =SUMPRODUCT((SalesData[MonthNum]=$A$47)*(($B$6="All")+(SalesData[Year]=$B$6))*(($C$6="All")+(SalesData[Quarter]=$C$6))*(($E$6="All")+(SalesData[Region]=$E$6))*(($F$6="All")+(SalesData[Category]=$F$6))*(($G$6="All")+(SalesData[Salesperson]=$G$6))*(($H$6="All")+(SalesData[Product]=$H$6))*SalesData[Cost]) -> 167684.87 | F47: =SUMPRODUCT((SalesData[MonthNum]=$A$47)*(($B$6="All")+(SalesData[Year]=$B$6))*(($C$6="All")+(SalesData[Quarter]=$C$6))*(($E$6="All")+(SalesData[Region]=$E$6))*(($F$6="All")+(SalesData[Category]=$F$6))*(($G$6="All")+(SalesData[Salesperson]=$G$6))*(($H$6="All")+(SalesData[Product]=$H$6))*SalesData[Profit]) -> 102774.62 | G47: =IFERROR(B47/SUM($B$42:$B$53),0) -> 0.055036363 | H47: =IF(NOT(ISNUMBER($B$6)),"n/a",IF($B$6<=2022,"n/a",IFERROR((B47-SUMPRODUCT((SalesData[MonthNum]=$A$47)*(SalesData[Year]=$B$6-1)*(($C$6="All")+(SalesData[Quarter]=$C$6))*(($D$6="All")+(SalesData[Month]=$D$6))*(($E$6="All")+(SalesData[Region]=$E$6))*(($F$6="All")+(SalesData[Category]=$F$6))*(($G$6="All")+(SalesData[Salesperson]=$G$6))*(($H$6="All")+(SalesData[Product]=$H$6))*SalesData[Revenue]))/SUMPRODUCT((SalesData[MonthNum]=$A$47)*(SalesData[Year]=$B$6-1)*(($C$6="All")+(SalesData[Quarter]=$C$6))*(($D$6="All")+(SalesData[Month]=$D$6))*(($E$6="All")+(SalesData[Region]=$E$6))*(($F$6="All")+(SalesData[Category]=$F$6))*(($G$6="All")+(SalesData[Salesperson]=$G$6))*(($H$6="All")+(SalesData[Product]=$H$6))*SalesData[Revenue]),"n/a"))) -> -0.15934935 | I47: =B47*Dashboard!$AB$2 -> 270459.49 | J47: =F47*Dashboard!$AB$2 -> 102774.62
A48: 7 | B48: =SUMPRODUCT((SalesData[MonthNum]=$A$48)*(($B$6="All")+(SalesData[Year]=$B$6))*(($C$6="All")+(SalesData[Quarter]=$C$6))*(($E$6="All")+(SalesData[Region]=$E$6))*(($F$6="All")+(SalesData[Category]=$F$6))*(($G$6="All")+(SalesData[Salesperson]=$G$6))*(($H$6="All")+(SalesData[Product]=$H$6))*SalesData[Revenue]) -> 490806.4 | C48: =SUMPRODUCT((SalesData[MonthNum]=$A$48)*(($B$6="All")+(SalesData[Year]=$B$6))*(($C$6="All")+(SalesData[Quarter]=$C$6))*(($E$6="All")+(SalesData[Region]=$E$6))*(($F$6="All")+(SalesData[Category]=$F$6))*(($G$6="All")+(SalesData[Salesperson]=$G$6))*(($H$6="All")+(SalesData[Product]=$H$6))*((SalesData[Units]<>0))) -> 15 | D48: =SUMPRODUCT((SalesData[MonthNum]=$A$48)*(($B$6="All")+(SalesData[Year]=$B$6))*(($C$6="All")+(SalesData[Quarter]=$C$6))*(($E$6="All")+(SalesData[Region]=$E$6))*(($F$6="All")+(SalesData[Category]=$F$6))*(($G$6="All")+(SalesData[Salesperson]=$G$6))*(($H$6="All")+(SalesData[Product]=$H$6))*SalesData[Units]) -> 325 | E48: =SUMPRODUCT((SalesData[MonthNum]=$A$48)*(($B$6="All")+(SalesData[Year]=$B$6))*(($C$6="All")+(SalesData[Quarter]=$C$6))*(($E$6="All")+(SalesData[Region]=$E$6))*(($F$6="All")+(SalesData[Category]=$F$6))*(($G$6="All")+(SalesData[Salesperson]=$G$6))*(($H$6="All")+(SalesData[Product]=$H$6))*SalesData[Cost]) -> 304299.96 | F48: =SUMPRODUCT((SalesData[MonthNum]=$A$48)*(($B$6="All")+(SalesData[Year]=$B$6))*(($C$6="All")+(SalesData[Quarter]=$C$6))*(($E$6="All")+(SalesData[Region]=$E$6))*(($F$6="All")+(SalesData[Category]=$F$6))*(($G$6="All")+(SalesData[Salesperson]=$G$6))*(($H$6="All")+(SalesData[Product]=$H$6))*SalesData[Profit]) -> 186506.44 | G48: =IFERROR(B48/SUM($B$42:$B$53),0) -> 0.099875212 | H48: =IF(NOT(ISNUMBER($B$6)),"n/a",IF($B$6<=2022,"n/a",IFERROR((B48-SUMPRODUCT((SalesData[MonthNum]=$A$48)*(SalesData[Year]=$B$6-1)*(($C$6="All")+(SalesData[Quarter]=$C$6))*(($D$6="All")+(SalesData[Month]=$D$6))*(($E$6="All")+(SalesData[Region]=$E$6))*(($F$6="All")+(SalesData[Category]=$F$6))*(($G$6="All")+(SalesData[Salesperson]=$G$6))*(($H$6="All")+(SalesData[Product]=$H$6))*SalesData[Revenue]))/SUMPRODUCT((SalesData[MonthNum]=$A$48)*(SalesData[Year]=$B$6-1)*(($C$6="All")+(SalesData[Quarter]=$C$6))*(($D$6="All")+(SalesData[Month]=$D$6))*(($E$6="All")+(SalesData[Region]=$E$6))*(($F$6="All")+(SalesData[Category]=$F$6))*(($G$6="All")+(SalesData[Salesperson]=$G$6))*(($H$6="All")+(SalesData[Product]=$H$6))*SalesData[Revenue]),"n/a"))) -> 1.2448182 | I48: =B48*Dashboard!$AB$2 -> 490806.4 | J48: =F48*Dashboard!$AB$2 -> 186506.44
A49: 8 | B49: =SUMPRODUCT((SalesData[MonthNum]=$A$49)*(($B$6="All")+(SalesData[Year]=$B$6))*(($C$6="All")+(SalesData[Quarter]=$C$6))*(($E$6="All")+(SalesData[Region]=$E$6))*(($F$6="All")+(SalesData[Category]=$F$6))*(($G$6="All")+(SalesData[Salesperson]=$G$6))*(($H$6="All")+(SalesData[Product]=$H$6))*SalesData[Revenue]) -> 383846.59 | C49: =SUMPRODUCT((SalesData[MonthNum]=$A$49)*(($B$6="All")+(SalesData[Year]=$B$6))*(($C$6="All")+(SalesData[Quarter]=$C$6))*(($E$6="All")+(SalesData[Region]=$E$6))*(($F$6="All")+(SalesData[Category]=$F$6))*(($G$6="All")+(SalesData[Salesperson]=$G$6))*(($H$6="All")+(SalesData[Product]=$H$6))*((SalesData[Units]<>0))) -> 15 | D49: =SUMPRODUCT((SalesData[MonthNum]=$A$49)*(($B$6="All")+(SalesData[Year]=$B$6))*(($C$6="All")+(SalesData[Quarter]=$C$6))*(($E$6="All")+(SalesData[Region]=$E$6))*(($F$6="All")+(SalesData[Category]=$F$6))*(($G$6="All")+(SalesData[Salesperson]=$G$6))*(($H$6="All")+(SalesData[Product]=$H$6))*SalesData[Units]) -> 293 | E49: =SUMPRODUCT((SalesData[MonthNum]=$A$49)*(($B$6="All")+(SalesData[Year]=$B$6))*(($C$6="All")+(SalesData[Quarter]=$C$6))*(($E$6="All")+(SalesData[Region]=$E$6))*(($F$6="All")+(SalesData[Category]=$F$6))*(($G$6="All")+(SalesData[Salesperson]=$G$6))*(($H$6="All")+(SalesData[Product]=$H$6))*SalesData[Cost]) -> 237984.9 | F49: =SUMPRODUCT((SalesData[MonthNum]=$A$49)*(($B$6="All")+(SalesData[Year]=$B$6))*(($C$6="All")+(SalesData[Quarter]=$C$6))*(($E$6="All")+(SalesData[Region]=$E$6))*(($F$6="All")+(SalesData[Category]=$F$6))*(($G$6="All")+(SalesData[Salesperson]=$G$6))*(($H$6="All")+(SalesData[Product]=$H$6))*SalesData[Profit]) -> 145861.69 | G49: =IFERROR(B49/SUM($B$42:$B$53),0) -> 0.078109739 | H49: =IF(NOT(ISNUMBER($B$6)),"n/a",IF($B$6<=2022,"n/a",IFERROR((B49-SUMPRODUCT((SalesData[MonthNum]=$A$49)*(SalesData[Year]=$B$6-1)*(($C$6="All")+(SalesData[Quarter]=$C$6))*(($D$6="All")+(SalesData[Month]=$D$6))*(($E$6="All")+(SalesData[Region]=$E$6))*(($F$6="All")+(SalesData[Category]=$F$6))*(($G$6="All")+(SalesData[Salesperson]=$G$6))*(($H$6="All")+(SalesData[Product]=$H$6))*SalesData[Revenue]))/SUMPRODUCT((SalesData[MonthNum]=$A$49)*(SalesData[Year]=$B$6-1)*(($C$6="All")+(SalesData[Quarter]=$C$6))*(($D$6="All")+(SalesData[Month]=$D$6))*(($E$6="All")+(SalesData[Region]=$E$6))*(($F$6="All")+(SalesData[Category]=$F$6))*(($G$6="All")+(SalesData[Salesperson]=$G$6))*(($H$6="All")+(SalesData[Product]=$H$6))*SalesData[Revenue]),"n/a"))) -> 0.19381078 | I49: =B49*Dashboard!$AB$2 -> 383846.59 | J49: =F49*Dashboard!$AB$2 -> 145861.69
A50: 9 | B50: =SUMPRODUCT((SalesData[MonthNum]=$A$50)*(($B$6="All")+(SalesData[Year]=$B$6))*(($C$6="All")+(SalesData[Quarter]=$C$6))*(($E$6="All")+(SalesData[Region]=$E$6))*(($F$6="All")+(SalesData[Category]=$F$6))*(($G$6="All")+(SalesData[Salesperson]=$G$6))*(($H$6="All")+(SalesData[Product]=$H$6))*SalesData[Revenue]) -> 472693.69 | C50: =SUMPRODUCT((SalesData[MonthNum]=$A$50)*(($B$6="All")+(SalesData[Year]=$B$6))*(($C$6="All")+(SalesData[Quarter]=$C$6))*(($E$6="All")+(SalesData[Region]=$E$6))*(($F$6="All")+(SalesData[Category]=$F$6))*(($G$6="All")+(SalesData[Salesperson]=$G$6))*(($H$6="All")+(SalesData[Product]=$H$6))*((SalesData[Units]<>0))) -> 15 | D50: =SUMPRODUCT((SalesData[MonthNum]=$A$50)*(($B$6="All")+(SalesData[Year]=$B$6))*(($C$6="All")+(SalesData[Quarter]=$C$6))*(($E$6="All")+(SalesData[Region]=$E$6))*(($F$6="All")+(SalesData[Category]=$F$6))*(($G$6="All")+(SalesData[Salesperson]=$G$6))*(($H$6="All")+(SalesData[Product]=$H$6))*SalesData[Units]) -> 390 | E50: =SUMPRODUCT((SalesData[MonthNum]=$A$50)*(($B$6="All")+(SalesData[Year]=$B$6))*(($C$6="All")+(SalesData[Quarter]=$C$6))*(($E$6="All")+(SalesData[Region]=$E$6))*(($F$6="All")+(SalesData[Category]=$F$6))*(($G$6="All")+(SalesData[Salesperson]=$G$6))*(($H$6="All")+(SalesData[Product]=$H$6))*SalesData[Cost]) -> 293070.08 | F50: =SUMPRODUCT((SalesData[MonthNum]=$A$50)*(($B$6="All")+(SalesData[Year]=$B$6))*(($C$6="All")+(SalesData[Quarter]=$C$6))*(($E$6="All")+(SalesData[Region]=$E$6))*(($F$6="All")+(SalesData[Category]=$F$6))*(($G$6="All")+(SalesData[Salesperson]=$G$6))*(($H$6="All")+(SalesData[Product]=$H$6))*SalesData[Profit]) -> 179623.61 | G50: =IFERROR(B50/SUM($B$42:$B$53),0) -> 0.096189419 | H50: =IF(NOT(ISNUMBER($B$6)),"n/a",IF($B$6<=2022,"n/a",IFERROR((B50-SUMPRODUCT((SalesData[MonthNum]=$A$50)*(SalesData[Year]=$B$6-1)*(($C$6="All")+(SalesData[Quarter]=$C$6))*(($D$6="All")+(SalesData[Month]=$D$6))*(($E$6="All")+(SalesData[Region]=$E$6))*(($F$6="All")+(SalesData[Category]=$F$6))*(($G$6="All")+(SalesData[Salesperson]=$G$6))*(($H$6="All")+(SalesData[Product]=$H$6))*SalesData[Revenue]))/SUMPRODUCT((SalesData[MonthNum]=$A$50)*(SalesData[Year]=$B$6-1)*(($C$6="All")+(SalesData[Quarter]=$C$6))*(($D$6="All")+(SalesData[Month]=$D$6))*(($E$6="All")+(SalesData[Region]=$E$6))*(($F$6="All")+(SalesData[Category]=$F$6))*(($G$6="All")+(SalesData[Salesperson]=$G$6))*(($H$6="All")+(SalesData[Product]=$H$6))*SalesData[Revenue]),"n/a"))) -> 0.76635029 | I50: =B50*Dashboard!$AB$2 -> 472693.69 | J50: =F50*Dashboard!$AB$2 -> 179623.61
A51: 10 | B51: =SUMPRODUCT((SalesData[MonthNum]=$A$51)*(($B$6="All")+(SalesData[Year]=$B$6))*(($C$6="All")+(SalesData[Quarter]=$C$6))*(($E$6="All")+(SalesData[Region]=$E$6))*(($F$6="All")+(SalesData[Category]=$F$6))*(($G$6="All")+(SalesData[Salesperson]=$G$6))*(($H$6="All")+(SalesData[Product]=$H$6))*SalesData[Revenue]) -> 156417.44 | C51: =SUMPRODUCT((SalesData[MonthNum]=$A$51)*(($B$6="All")+(SalesData[Year]=$B$6))*(($C$6="All")+(SalesData[Quarter]=$C$6))*(($E$6="All")+(SalesData[Region]=$E$6))*(($F$6="All")+(SalesData[Category]=$F$6))*(($G$6="All")+(SalesData[Salesperson]=$G$6))*(($H$6="All")+(SalesData[Product]=$H$6))*((SalesData[Units]<>0))) -> 15 | D51: =SUMPRODUCT((SalesData[MonthNum]=$A$51)*(($B$6="All")+(SalesData[Year]=$B$6))*(($C$6="All")+(SalesData[Quarter]=$C$6))*(($E$6="All")+(SalesData[Region]=$E$6))*(($F$6="All")+(SalesData[Category]=$F$6))*(($G$6="All")+(SalesData[Salesperson]=$G$6))*(($H$6="All")+(SalesData[Product]=$H$6))*SalesData[Units]) -> 306 | E51: =SUMPRODUCT((SalesData[MonthNum]=$A$51)*(($B$6="All")+(SalesData[Year]=$B$6))*(($C$6="All")+(SalesData[Quarter]=$C$6))*(($E$6="All")+(SalesData[Region]=$E$6))*(($F$6="All")+(SalesData[Category]=$F$6))*(($G$6="All")+(SalesData[Salesperson]=$G$6))*(($H$6="All")+(SalesData[Product]=$H$6))*SalesData[Cost]) -> 96978.81 | F51: =SUMPRODUCT((SalesData[MonthNum]=$A$51)*(($B$6="All")+(SalesData[Year]=$B$6))*(($C$6="All")+(SalesData[Quarter]=$C$6))*(($E$6="All")+(SalesData[Region]=$E$6))*(($F$6="All")+(SalesData[Category]=$F$6))*(($G$6="All")+(SalesData[Salesperson]=$G$6))*(($H$6="All")+(SalesData[Product]=$H$6))*SalesData[Profit]) -> 59438.63 | G51: =IFERROR(B51/SUM($B$42:$B$53),0) -> 0.031829709 | H51: =IF(NOT(ISNUMBER($B$6)),"n/a",IF($B$6<=2022,"n/a",IFERROR((B51-SUMPRODUCT((SalesData[MonthNum]=$A$51)*(SalesData[Year]=$B$6-1)*(($C$6="All")+(SalesData[Quarter]=$C$6))*(($D$6="All")+(SalesData[Month]=$D$6))*(($E$6="All")+(SalesData[Region]=$E$6))*(($F$6="All")+(SalesData[Category]=$F$6))*(($G$6="All")+(SalesData[Salesperson]=$G$6))*(($H$6="All")+(SalesData[Product]=$H$6))*SalesData[Revenue]))/SUMPRODUCT((SalesData[MonthNum]=$A$51)*(SalesData[Year]=$B$6-1)*(($C$6="All")+(SalesData[Quarter]=$C$6))*(($D$6="All")+(SalesData[Month]=$D$6))*(($E$6="All")+(SalesData[Region]=$E$6))*(($F$6="All")+(SalesData[Category]=$F$6))*(($G$6="All")+(SalesData[Salesperson]=$G$6))*(($H$6="All")+(SalesData[Product]=$H$6))*SalesData[Revenue]),"n/a"))) -> 0.58722052 | I51: =B51*Dashboard!$AB$2 -> 156417.44 | J51: =F51*Dashboard!$AB$2 -> 59438.63
A52: 11 | B52: =SUMPRODUCT((SalesData[MonthNum]=$A$52)*(($B$6="All")+(SalesData[Year]=$B$6))*(($C$6="All")+(SalesData[Quarter]=$C$6))*(($E$6="All")+(SalesData[Region]=$E$6))*(($F$6="All")+(SalesData[Category]=$F$6))*(($G$6="All")+(SalesData[Salesperson]=$G$6))*(($H$6="All")+(SalesData[Product]=$H$6))*SalesData[Revenue]) -> 309229.52 | C52: =SUMPRODUCT((SalesData[MonthNum]=$A$52)*(($B$6="All")+(SalesData[Year]=$B$6))*(($C$6="All")+(SalesData[Quarter]=$C$6))*(($E$6="All")+(SalesData[Region]=$E$6))*(($F$6="All")+(SalesData[Category]=$F$6))*(($G$6="All")+(SalesData[Salesperson]=$G$6))*(($H$6="All")+(SalesData[Product]=$H$6))*((SalesData[Units]<>0))) -> 15 | D52: =SUMPRODUCT((SalesData[MonthNum]=$A$52)*(($B$6="All")+(SalesData[Year]=$B$6))*(($C$6="All")+(SalesData[Quarter]=$C$6))*(($E$6="All")+(SalesData[Region]=$E$6))*(($F$6="All")+(SalesData[Category]=$F$6))*(($G$6="All")+(SalesData[Salesperson]=$G$6))*(($H$6="All")+(SalesData[Product]=$H$6))*SalesData[Units]) -> 301 | E52: =SUMPRODUCT((SalesData[MonthNum]=$A$52)*(($B$6="All")+(SalesData[Year]=$B$6))*(($C$6="All")+(SalesData[Quarter]=$C$6))*(($E$6="All")+(SalesData[Region]=$E$6))*(($F$6="All")+(SalesData[Category]=$F$6))*(($G$6="All")+(SalesData[Salesperson]=$G$6))*(($H$6="All")+(SalesData[Product]=$H$6))*SalesData[Cost]) -> 191722.31 | F52: =SUMPRODUCT((SalesData[MonthNum]=$A$52)*(($B$6="All")+(SalesData[Year]=$B$6))*(($C$6="All")+(SalesData[Quarter]=$C$6))*(($E$6="All")+(SalesData[Region]=$E$6))*(($F$6="All")+(SalesData[Category]=$F$6))*(($G$6="All")+(SalesData[Salesperson]=$G$6))*(($H$6="All")+(SalesData[Product]=$H$6))*SalesData[Profit]) -> 117507.21 | G52: =IFERROR(B52/SUM($B$42:$B$53),0) -> 0.062925756 | H52: =IF(NOT(ISNUMBER($B$6)),"n/a",IF($B$6<=2022,"n/a",IFERROR((B52-SUMPRODUCT((SalesData[MonthNum]=$A$52)*(SalesData[Year]=$B$6-1)*(($C$6="All")+(SalesData[Quarter]=$C$6))*(($D$6="All")+(SalesData[Month]=$D$6))*(($E$6="All")+(SalesData[Region]=$E$6))*(($F$6="All")+(SalesData[Category]=$F$6))*(($G$6="All")+(SalesData[Salesperson]=$G$6))*(($H$6="All")+(SalesData[Product]=$H$6))*SalesData[Revenue]))/SUMPRODUCT((SalesData[MonthNum]=$A$52)*(SalesData[Year]=$B$6-1)*(($C$6="All")+(SalesData[Quarter]=$C$6))*(($D$6="All")+(SalesData[Month]=$D$6))*(($E$6="All")+(SalesData[Region]=$E$6))*(($F$6="All")+(SalesData[Category]=$F$6))*(($G$6="All")+(SalesData[Salesperson]=$G$6))*(($H$6="All")+(SalesData[Product]=$H$6))*SalesData[Revenue]),"n/a"))) -> -0.23759644 | I52: =B52*Dashboard!$AB$2 -> 309229.52 | J52: =F52*Dashboard!$AB$2 -> 117507.21
A53: 12 | B53: =SUMPRODUCT((SalesData[MonthNum]=$A$53)*(($B$6="All")+(SalesData[Year]=$B$6))*(($C$6="All")+(SalesData[Quarter]=$C$6))*(($E$6="All")+(SalesData[Region]=$E$6))*(($F$6="All")+(SalesData[Category]=$F$6))*(($G$6="All")+(SalesData[Salesperson]=$G$6))*(($H$6="All")+(SalesData[Product]=$H$6))*SalesData[Revenue]) -> 931831.95 | C53: =SUMPRODUCT((SalesData[MonthNum]=$A$53)*(($B$6="All")+(SalesData[Year]=$B$6))*(($C$6="All")+(SalesData[Quarter]=$C$6))*(($E$6="All")+(SalesData[Region]=$E$6))*(($F$6="All")+(SalesData[Category]=$F$6))*(($G$6="All")+(SalesData[Salesperson]=$G$6))*(($H$6="All")+(SalesData[Product]=$H$6))*((SalesData[Units]<>0))) -> 15 | D53: =SUMPRODUCT((SalesData[MonthNum]=$A$53)*(($B$6="All")+(SalesData[Year]=$B$6))*(($C$6="All")+(SalesData[Quarter]=$C$6))*(($E$6="All")+(SalesData[Region]=$E$6))*(($F$6="All")+(SalesData[Category]=$F$6))*(($G$6="All")+(SalesData[Salesperson]=$G$6))*(($H$6="All")+(SalesData[Product]=$H$6))*SalesData[Units]) -> 540 | E53: =SUMPRODUCT((SalesData[MonthNum]=$A$53)*(($B$6="All")+(SalesData[Year]=$B$6))*(($C$6="All")+(SalesData[Quarter]=$C$6))*(($E$6="All")+(SalesData[Region]=$E$6))*(($F$6="All")+(SalesData[Category]=$F$6))*(($G$6="All")+(SalesData[Salesperson]=$G$6))*(($H$6="All")+(SalesData[Product]=$H$6))*SalesData[Cost]) -> 577735.81 | F53: =SUMPRODUCT((SalesData[MonthNum]=$A$53)*(($B$6="All")+(SalesData[Year]=$B$6))*(($C$6="All")+(SalesData[Quarter]=$C$6))*(($E$6="All")+(SalesData[Region]=$E$6))*(($F$6="All")+(SalesData[Category]=$F$6))*(($G$6="All")+(SalesData[Salesperson]=$G$6))*(($H$6="All")+(SalesData[Product]=$H$6))*SalesData[Profit]) -> 354096.14 | G53: =IFERROR(B53/SUM($B$42:$B$53),0) -> 0.18962042 | H53: =IF(NOT(ISNUMBER($B$6)),"n/a",IF($B$6<=2022,"n/a",IFERROR((B53-SUMPRODUCT((SalesData[MonthNum]=$A$53)*(SalesData[Year]=$B$6-1)*(($C$6="All")+(SalesData[Quarter]=$C$6))*(($D$6="All")+(SalesData[Month]=$D$6))*(($E$6="All")+(SalesData[Region]=$E$6))*(($F$6="All")+(SalesData[Category]=$F$6))*(($G$6="All")+(SalesData[Salesperson]=$G$6))*(($H$6="All")+(SalesData[Product]=$H$6))*SalesData[Revenue]))/SUMPRODUCT((SalesData[MonthNum]=$A$53)*(SalesData[Year]=$B$6-1)*(($C$6="All")+(SalesData[Quarter]=$C$6))*(($D$6="All")+(SalesData[Month]=$D$6))*(($E$6="All")+(SalesData[Region]=$E$6))*(($F$6="All")+(SalesData[Category]=$F$6))*(($G$6="All")+(SalesData[Salesperson]=$G$6))*(($H$6="All")+(SalesData[Product]=$H$6))*SalesData[Revenue]),"n/a"))) -> 1.7299784 | I53: =B53*Dashboard!$AB$2 -> 931831.95 | J53: =F53*Dashboard!$AB$2 -> 354096.14
A54: TOTAL | B54: =SUM(B42:B53) -> 4914196.3 | C54: =SUM(C42:C53) -> 180 | D54: =SUM(D42:D53) -> 3831 | E54: =SUM(E42:E53) -> 3046801.7 | F54: =SUM(F42:F53) -> 1867394.6 | G54: - | H54: - | I54: =SUM(I42:I53) -> 4914196.3 | J54: =SUM(J42:J53) -> 1867394.6
A56: 4 | QUARTER TOTALS
A57: Quarter | B57: Revenue | C57: Orders | D57: Units | E57: Profit | F57: SHARE % | G57: Revenue USD
A58: Q1 | B58: =SUMPRODUCT((SalesData[Quarter]=$A$58)*(($B$6="All")+(SalesData[Year]=$B$6))*(($D$6="All")+(SalesData[Month]=$D$6))*(($E$6="All")+(SalesData[Region]=$E$6))*(($F$6="All")+(SalesData[Category]=$F$6))*(($G$6="All")+(SalesData[Salesperson]=$G$6))*(($H$6="All")+(SalesData[Product]=$H$6))*SalesData[Revenue]) -> 1258730.4 | C58: =SUMPRODUCT((SalesData[Quarter]=$A$58)*(($B$6="All")+(SalesData[Year]=$B$6))*(($D$6="All")+(SalesData[Month]=$D$6))*(($E$6="All")+(SalesData[Region]=$E$6))*(($F$6="All")+(SalesData[Category]=$F$6))*(($G$6="All")+(SalesData[Salesperson]=$G$6))*(($H$6="All")+(SalesData[Product]=$H$6))*((SalesData[Units]<>0))) -> 45 | D58: =SUMPRODUCT((SalesData[Quarter]=$A$58)*(($B$6="All")+(SalesData[Year]=$B$6))*(($D$6="All")+(SalesData[Month]=$D$6))*(($E$6="All")+(SalesData[Region]=$E$6))*(($F$6="All")+(SalesData[Category]=$F$6))*(($G$6="All")+(SalesData[Salesperson]=$G$6))*(($H$6="All")+(SalesData[Product]=$H$6))*SalesData[Units]) -> 866 | E58: =SUMPRODUCT((SalesData[Quarter]=$A$58)*(($B$6="All")+(SalesData[Year]=$B$6))*(($D$6="All")+(SalesData[Month]=$D$6))*(($E$6="All")+(SalesData[Region]=$E$6))*(($F$6="All")+(SalesData[Category]=$F$6))*(($G$6="All")+(SalesData[Salesperson]=$G$6))*(($H$6="All")+(SalesData[Product]=$H$6))*SalesData[Profit]) -> 478317.54 | F58: =IFERROR(B58/SUM($B$58:$B$61),0) -> 0.25614166 | G58: =B58*Dashboard!$AB$2 -> 1258730.4
A59: Q2 | B59: =SUMPRODUCT((SalesData[Quarter]=$A$59)*(($B$6="All")+(SalesData[Year]=$B$6))*(($D$6="All")+(SalesData[Month]=$D$6))*(($E$6="All")+(SalesData[Region]=$E$6))*(($F$6="All")+(SalesData[Category]=$F$6))*(($G$6="All")+(SalesData[Salesperson]=$G$6))*(($H$6="All")+(SalesData[Product]=$H$6))*SalesData[Revenue]) -> 910640.34 | C59: =SUMPRODUCT((SalesData[Quarter]=$A$59)*(($B$6="All")+(SalesData[Year]=$B$6))*(($D$6="All")+(SalesData[Month]=$D$6))*(($E$6="All")+(SalesData[Region]=$E$6))*(($F$6="All")+(SalesData[Category]=$F$6))*(($G$6="All")+(SalesData[Salesperson]=$G$6))*(($H$6="All")+(SalesData[Product]=$H$6))*((SalesData[Units]<>0))) -> 45 | D59: =SUMPRODUCT((SalesData[Quarter]=$A$59)*(($B$6="All")+(SalesData[Year]=$B$6))*(($D$6="All")+(SalesData[Month]=$D$6))*(($E$6="All")+(SalesData[Region]=$E$6))*(($F$6="All")+(SalesData[Category]=$F$6))*(($G$6="All")+(SalesData[Salesperson]=$G$6))*(($H$6="All")+(SalesData[Product]=$H$6))*SalesData[Units]) -> 810 | E59: =SUMPRODUCT((SalesData[Quarter]=$A$59)*(($B$6="All")+(SalesData[Year]=$B$6))*(($D$6="All")+(SalesData[Month]=$D$6))*(($E$6="All")+(SalesData[Region]=$E$6))*(($F$6="All")+(SalesData[Category]=$F$6))*(($G$6="All")+(SalesData[Salesperson]=$G$6))*(($H$6="All")+(SalesData[Product]=$H$6))*SalesData[Profit]) -> 346043.36 | F59: =IFERROR(B59/SUM($B$58:$B$61),0) -> 0.18530809 | G59: =B59*Dashboard!$AB$2 -> 910640.34
A60: Q3 | B60: =SUMPRODUCT((SalesData[Quarter]=$A$60)*(($B$6="All")+(SalesData[Year]=$B$6))*(($D$6="All")+(SalesData[Month]=$D$6))*(($E$6="All")+(SalesData[Region]=$E$6))*(($F$6="All")+(SalesData[Category]=$F$6))*(($G$6="All")+(SalesData[Salesperson]=$G$6))*(($H$6="All")+(SalesData[Product]=$H$6))*SalesData[Revenue]) -> 1347346.7 | C60: =SUMPRODUCT((SalesData[Quarter]=$A$60)*(($B$6="All")+(SalesData[Year]=$B$6))*(($D$6="All")+(SalesData[Month]=$D$6))*(($E$6="All")+(SalesData[Region]=$E$6))*(($F$6="All")+(SalesData[Category]=$F$6))*(($G$6="All")+(SalesData[Salesperson]=$G$6))*(($H$6="All")+(SalesData[Product]=$H$6))*((SalesData[Units]<>0))) -> 45 | D60: =SUMPRODUCT((SalesData[Quarter]=$A$60)*(($B$6="All")+(SalesData[Year]=$B$6))*(($D$6="All")+(SalesData[Month]=$D$6))*(($E$6="All")+(SalesData[Region]=$E$6))*(($F$6="All")+(SalesData[Category]=$F$6))*(($G$6="All")+(SalesData[Salesperson]=$G$6))*(($H$6="All")+(SalesData[Product]=$H$6))*SalesData[Units]) -> 1008 | E60: =SUMPRODUCT((SalesData[Quarter]=$A$60)*(($B$6="All")+(SalesData[Year]=$B$6))*(($D$6="All")+(SalesData[Month]=$D$6))*(($E$6="All")+(SalesData[Region]=$E$6))*(($F$6="All")+(SalesData[Category]=$F$6))*(($G$6="All")+(SalesData[Salesperson]=$G$6))*(($H$6="All")+(SalesData[Product]=$H$6))*SalesData[Profit]) -> 511991.74 | F60: =IFERROR(B60/SUM($B$58:$B$61),0) -> 0.27417437 | G60: =B60*Dashboard!$AB$2 -> 1347346.7
A61: Q4 | B61: =SUMPRODUCT((SalesData[Quarter]=$A$61)*(($B$6="All")+(SalesData[Year]=$B$6))*(($D$6="All")+(SalesData[Month]=$D$6))*(($E$6="All")+(SalesData[Region]=$E$6))*(($F$6="All")+(SalesData[Category]=$F$6))*(($G$6="All")+(SalesData[Salesperson]=$G$6))*(($H$6="All")+(SalesData[Product]=$H$6))*SalesData[Revenue]) -> 1397478.9 | C61: =SUMPRODUCT((SalesData[Quarter]=$A$61)*(($B$6="All")+(SalesData[Year]=$B$6))*(($D$6="All")+(SalesData[Month]=$D$6))*(($E$6="All")+(SalesData[Region]=$E$6))*(($F$6="All")+(SalesData[Category]=$F$6))*(($G$6="All")+(SalesData[Salesperson]=$G$6))*(($H$6="All")+(SalesData[Product]=$H$6))*((SalesData[Units]<>0))) -> 45 | D61: =SUMPRODUCT((SalesData[Quarter]=$A$61)*(($B$6="All")+(SalesData[Year]=$B$6))*(($D$6="All")+(SalesData[Month]=$D$6))*(($E$6="All")+(SalesData[Region]=$E$6))*(($F$6="All")+(SalesData[Category]=$F$6))*(($G$6="All")+(SalesData[Salesperson]=$G$6))*(($H$6="All")+(SalesData[Product]=$H$6))*SalesData[Units]) -> 1147 | E61: =SUMPRODUCT((SalesData[Quarter]=$A$61)*(($B$6="All")+(SalesData[Year]=$B$6))*(($D$6="All")+(SalesData[Month]=$D$6))*(($E$6="All")+(SalesData[Region]=$E$6))*(($F$6="All")+(SalesData[Category]=$F$6))*(($G$6="All")+(SalesData[Salesperson]=$G$6))*(($H$6="All")+(SalesData[Product]=$H$6))*SalesData[Profit]) -> 531041.98 | F61: =IFERROR(B61/SUM($B$58:$B$61),0) -> 0.28437588 | G61: =B61*Dashboard!$AB$2 -> 1397478.9
A62: TOTAL | B62: =SUM(B58:B61) -> 4914196.3 | C62: =SUM(C58:C61) -> 180 | D62: =SUM(D58:D61) -> 3831 | E62: =SUM(E58:E61) -> 1867394.6 | G62: =SUM(G58:G61) -> 4914196.3
A64: 5 | REGION TOTALS
A65: Region | B65: Revenue | C65: Orders | D65: Units | E65: SHARE % | F65: Revenue USD
A66: North | B66: =SUMPRODUCT((SalesData[Region]=$A$66)*(($B$6="All")+(SalesData[Year]=$B$6))*(($C$6="All")+(SalesData[Quarter]=$C$6))*(($D$6="All")+(SalesData[Month]=$D$6))*(($F$6="All")+(SalesData[Category]=$F$6))*(($G$6="All")+(SalesData[Salesperson]=$G$6))*(($H$6="All")+(SalesData[Product]=$H$6))*SalesData[Revenue]) -> 644006.04 | C66: =SUMPRODUCT((SalesData[Region]=$A$66)*(($B$6="All")+(SalesData[Year]=$B$6))*(($C$6="All")+(SalesData[Quarter]=$C$6))*(($D$6="All")+(SalesData[Month]=$D$6))*(($F$6="All")+(SalesData[Category]=$F$6))*(($G$6="All")+(SalesData[Salesperson]=$G$6))*(($H$6="All")+(SalesData[Product]=$H$6))*((SalesData[Units]<>0))) -> 25 | D66: =SUMPRODUCT((SalesData[Region]=$A$66)*(($B$6="All")+(SalesData[Year]=$B$6))*(($C$6="All")+(SalesData[Quarter]=$C$6))*(($D$6="All")+(SalesData[Month]=$D$6))*(($F$6="All")+(SalesData[Category]=$F$6))*(($G$6="All")+(SalesData[Salesperson]=$G$6))*(($H$6="All")+(SalesData[Product]=$H$6))*SalesData[Units]) -> 620 | E66: =IFERROR(B66/SUM($B$66:$B$70),0) -> 0.13105012 | F66: =B66*Dashboard!$AB$2 -> 644006.04
A67: South | B67: =SUMPRODUCT((SalesData[Region]=$A$67)*(($B$6="All")+(SalesData[Year]=$B$6))*(($C$6="All")+(SalesData[Quarter]=$C$6))*(($D$6="All")+(SalesData[Month]=$D$6))*(($F$6="All")+(SalesData[Category]=$F$6))*(($G$6="All")+(SalesData[Salesperson]=$G$6))*(($H$6="All")+(SalesData[Product]=$H$6))*SalesData[Revenue]) -> 1432864.9 | C67: =SUMPRODUCT((SalesData[Region]=$A$67)*(($B$6="All")+(SalesData[Year]=$B$6))*(($C$6="All")+(SalesData[Quarter]=$C$6))*(($D$6="All")+(SalesData[Month]=$D$6))*(($F$6="All")+(SalesData[Category]=$F$6))*(($G$6="All")+(SalesData[Salesperson]=$G$6))*(($H$6="All")+(SalesData[Product]=$H$6))*((SalesData[Units]<>0))) -> 41 | D67: =SUMPRODUCT((SalesData[Region]=$A$67)*(($B$6="All")+(SalesData[Year]=$B$6))*(($C$6="All")+(SalesData[Quarter]=$C$6))*(($D$6="All")+(SalesData[Month]=$D$6))*(($F$6="All")+(SalesData[Category]=$F$6))*(($G$6="All")+(SalesData[Salesperson]=$G$6))*(($H$6="All")+(SalesData[Product]=$H$6))*SalesData[Units]) -> 804 | E67: =IFERROR(B67/SUM($B$66:$B$70),0) -> 0.29157666 | F67: =B67*Dashboard!$AB$2 -> 1432864.9
A68: East | B68: =SUMPRODUCT((SalesData[Region]=$A$68)*(($B$6="All")+(SalesData[Year]=$B$6))*(($C$6="All")+(SalesData[Quarter]=$C$6))*(($D$6="All")+(SalesData[Month]=$D$6))*(($F$6="All")+(SalesData[Category]=$F$6))*(($G$6="All")+(SalesData[Salesperson]=$G$6))*(($H$6="All")+(SalesData[Product]=$H$6))*SalesData[Revenue]) -> 837545.24 | C68: =SUMPRODUCT((SalesData[Region]=$A$68)*(($B$6="All")+(SalesData[Year]=$B$6))*(($C$6="All")+(SalesData[Quarter]=$C$6))*(($D$6="All")+(SalesData[Month]=$D$6))*(($F$6="All")+(SalesData[Category]=$F$6))*(($G$6="All")+(SalesData[Salesperson]=$G$6))*(($H$6="All")+(SalesData[Product]=$H$6))*((SalesData[Units]<>0))) -> 30 | D68: =SUMPRODUCT((SalesData[Region]=$A$68)*(($B$6="All")+(SalesData[Year]=$B$6))*(($C$6="All")+(SalesData[Quarter]=$C$6))*(($D$6="All")+(SalesData[Month]=$D$6))*(($F$6="All")+(SalesData[Category]=$F$6))*(($G$6="All")+(SalesData[Salesperson]=$G$6))*(($H$6="All")+(SalesData[Product]=$H$6))*SalesData[Units]) -> 667 | E68: =IFERROR(B68/SUM($B$66:$B$70),0) -> 0.17043382 | F68: =B68*Dashboard!$AB$2 -> 837545.24
A69: West | B69: =SUMPRODUCT((SalesData[Region]=$A$69)*(($B$6="All")+(SalesData[Year]=$B$6))*(($C$6="All")+(SalesData[Quarter]=$C$6))*(($D$6="All")+(SalesData[Month]=$D$6))*(($F$6="All")+(SalesData[Category]=$F$6))*(($G$6="All")+(SalesData[Salesperson]=$G$6))*(($H$6="All")+(SalesData[Product]=$H$6))*SalesData[Revenue]) -> 1083542.3 | C69: =SUMPRODUCT((SalesData[Region]=$A$69)*(($B$6="All")+(SalesData[Year]=$B$6))*(($C$6="All")+(SalesData[Quarter]=$C$6))*(($D$6="All")+(SalesData[Month]=$D$6))*(($F$6="All")+(SalesData[Category]=$F$6))*(($G$6="All")+(SalesData[Salesperson]=$G$6))*(($H$6="All")+(SalesData[Product]=$H$6))*((SalesData[Units]<>0))) -> 51 | D69: =SUMPRODUCT((SalesData[Region]=$A$69)*(($B$6="All")+(SalesData[Year]=$B$6))*(($C$6="All")+(SalesData[Quarter]=$C$6))*(($D$6="All")+(SalesData[Month]=$D$6))*(($F$6="All")+(SalesData[Category]=$F$6))*(($G$6="All")+(SalesData[Salesperson]=$G$6))*(($H$6="All")+(SalesData[Product]=$H$6))*SalesData[Units]) -> 1005 | E69: =IFERROR(B69/SUM($B$66:$B$70),0) -> 0.22049227 | F69: =B69*Dashboard!$AB$2 -> 1083542.3
A70: Central | B70: =SUMPRODUCT((SalesData[Region]=$A$70)*(($B$6="All")+(SalesData[Year]=$B$6))*(($C$6="All")+(SalesData[Quarter]=$C$6))*(($D$6="All")+(SalesData[Month]=$D$6))*(($F$6="All")+(SalesData[Category]=$F$6))*(($G$6="All")+(SalesData[Salesperson]=$G$6))*(($H$6="All")+(SalesData[Product]=$H$6))*SalesData[Revenue]) -> 916237.79 | C70: =SUMPRODUCT((SalesData[Region]=$A$70)*(($B$6="All")+(SalesData[Year]=$B$6))*(($C$6="All")+(SalesData[Quarter]=$C$6))*(($D$6="All")+(SalesData[Month]=$D$6))*(($F$6="All")+(SalesData[Category]=$F$6))*(($G$6="All")+(SalesData[Salesperson]=$G$6))*(($H$6="All")+(SalesData[Product]=$H$6))*((SalesData[Units]<>0))) -> 33 | D70: =SUMPRODUCT((SalesData[Region]=$A$70)*(($B$6="All")+(SalesData[Year]=$B$6))*(($C$6="All")+(SalesData[Quarter]=$C$6))*(($D$6="All")+(SalesData[Month]=$D$6))*(($F$6="All")+(SalesData[Category]=$F$6))*(($G$6="All")+(SalesData[Salesperson]=$G$6))*(($H$6="All")+(SalesData[Product]=$H$6))*SalesData[Units]) -> 735 | E70: =IFERROR(B70/SUM($B$66:$B$70),0) -> 0.18644713 | F70: =B70*Dashboard!$AB$2 -> 916237.79
A71: TOTAL | B71: =SUM(B66:B70) -> 4914196.3 | F71: =SUM(F66:F70) -> 4914196.3
A73: 6 | CATEGORY TOTALS
A74: Category | B74: Revenue | C74: Profit | D74: Margin % | E74: SHARE % | F74: Revenue USD
A75: Grocery | B75: =SUMPRODUCT((SalesData[Category]=$A$75)*(($B$6="All")+(SalesData[Year]=$B$6))*(($C$6="All")+(SalesData[Quarter]=$C$6))*(($D$6="All")+(SalesData[Month]=$D$6))*(($E$6="All")+(SalesData[Region]=$E$6))*(($G$6="All")+(SalesData[Salesperson]=$G$6))*(($H$6="All")+(SalesData[Product]=$H$6))*SalesData[Revenue]) -> 83951.66 | C75: =SUMPRODUCT((SalesData[Category]=$A$75)*(($B$6="All")+(SalesData[Year]=$B$6))*(($C$6="All")+(SalesData[Quarter]=$C$6))*(($D$6="All")+(SalesData[Month]=$D$6))*(($E$6="All")+(SalesData[Region]=$E$6))*(($G$6="All")+(SalesData[Salesperson]=$G$6))*(($H$6="All")+(SalesData[Product]=$H$6))*SalesData[Profit]) -> 31901.65 | D75: =IFERROR(C75/B75,0) -> 0.38000023 | E75: =IFERROR(B75/SUM($B$75:$B$79),0) -> 0.017083497 | F75: =B75*Dashboard!$AB$2 -> 83951.66
A76: Furniture | B76: =SUMPRODUCT((SalesData[Category]=$A$76)*(($B$6="All")+(SalesData[Year]=$B$6))*(($C$6="All")+(SalesData[Quarter]=$C$6))*(($D$6="All")+(SalesData[Month]=$D$6))*(($E$6="All")+(SalesData[Region]=$E$6))*(($G$6="All")+(SalesData[Salesperson]=$G$6))*(($H$6="All")+(SalesData[Product]=$H$6))*SalesData[Revenue]) -> 2004450.3 | C76: =SUMPRODUCT((SalesData[Category]=$A$76)*(($B$6="All")+(SalesData[Year]=$B$6))*(($C$6="All")+(SalesData[Quarter]=$C$6))*(($D$6="All")+(SalesData[Month]=$D$6))*(($E$6="All")+(SalesData[Region]=$E$6))*(($G$6="All")+(SalesData[Salesperson]=$G$6))*(($H$6="All")+(SalesData[Product]=$H$6))*SalesData[Profit]) -> 761691.14 | D76: =IFERROR(C76/B76,0) -> 0.38000001 | E76: =IFERROR(B76/SUM($B$75:$B$79),0) -> 0.40788976 | F76: =B76*Dashboard!$AB$2 -> 2004450.3
A77: Clothing | B77: =SUMPRODUCT((SalesData[Category]=$A$77)*(($B$6="All")+(SalesData[Year]=$B$6))*(($C$6="All")+(SalesData[Quarter]=$C$6))*(($D$6="All")+(SalesData[Month]=$D$6))*(($E$6="All")+(SalesData[Region]=$E$6))*(($G$6="All")+(SalesData[Salesperson]=$G$6))*(($H$6="All")+(SalesData[Product]=$H$6))*SalesData[Revenue]) -> 216590.41 | C77: =SUMPRODUCT((SalesData[Category]=$A$77)*(($B$6="All")+(SalesData[Year]=$B$6))*(($C$6="All")+(SalesData[Quarter]=$C$6))*(($D$6="All")+(SalesData[Month]=$D$6))*(($E$6="All")+(SalesData[Region]=$E$6))*(($G$6="All")+(SalesData[Salesperson]=$G$6))*(($H$6="All")+(SalesData[Product]=$H$6))*SalesData[Profit]) -> 82304.36 | D77: =IFERROR(C77/B77,0) -> 0.38000002 | E77: =IFERROR(B77/SUM($B$75:$B$79),0) -> 0.044074432 | F77: =B77*Dashboard!$AB$2 -> 216590.41
A78: Sports | B78: =SUMPRODUCT((SalesData[Category]=$A$78)*(($B$6="All")+(SalesData[Year]=$B$6))*(($C$6="All")+(SalesData[Quarter]=$C$6))*(($D$6="All")+(SalesData[Month]=$D$6))*(($E$6="All")+(SalesData[Region]=$E$6))*(($G$6="All")+(SalesData[Salesperson]=$G$6))*(($H$6="All")+(SalesData[Product]=$H$6))*SalesData[Revenue]) -> 171530.69 | C78: =SUMPRODUCT((SalesData[Category]=$A$78)*(($B$6="All")+(SalesData[Year]=$B$6))*(($C$6="All")+(SalesData[Quarter]=$C$6))*(($D$6="All")+(SalesData[Month]=$D$6))*(($E$6="All")+(SalesData[Region]=$E$6))*(($G$6="All")+(SalesData[Salesperson]=$G$6))*(($H$6="All")+(SalesData[Product]=$H$6))*SalesData[Profit]) -> 65181.65 | D78: =IFERROR(C78/B78,0) -> 0.37999993 | E78: =IFERROR(B78/SUM($B$75:$B$79),0) -> 0.034905136 | F78: =B78*Dashboard!$AB$2 -> 171530.69
A79: Electronics | B79: =SUMPRODUCT((SalesData[Category]=$A$79)*(($B$6="All")+(SalesData[Year]=$B$6))*(($C$6="All")+(SalesData[Quarter]=$C$6))*(($D$6="All")+(SalesData[Month]=$D$6))*(($E$6="All")+(SalesData[Region]=$E$6))*(($G$6="All")+(SalesData[Salesperson]=$G$6))*(($H$6="All")+(SalesData[Product]=$H$6))*SalesData[Revenue]) -> 2437673.2 | C79: =SUMPRODUCT((SalesData[Category]=$A$79)*(($B$6="All")+(SalesData[Year]=$B$6))*(($C$6="All")+(SalesData[Quarter]=$C$6))*(($D$6="All")+(SalesData[Month]=$D$6))*(($E$6="All")+(SalesData[Region]=$E$6))*(($G$6="All")+(SalesData[Salesperson]=$G$6))*(($H$6="All")+(SalesData[Product]=$H$6))*SalesData[Profit]) -> 926315.82 | D79: =IFERROR(C79/B79,0) -> 0.38 | E79: =IFERROR(B79/SUM($B$75:$B$79),0) -> 0.49604718 | F79: =B79*Dashboard!$AB$2 -> 2437673.2
A80: TOTAL | B80: =SUM(B75:B79) -> 4914196.3 | C80: =SUM(C75:C79) -> 1867394.6 | F80: =SUM(F75:F79) -> 4914196.3
A82: 7 | SALESPERSON TOTALS
A83: Salesperson | B83: Revenue | C83: Orders | D83: Units | E83: SHARE % | F83: Revenue USD
A84: Ahmed Hassan | B84: =SUMPRODUCT((SalesData[Salesperson]=$A$84)*(($B$6="All")+(SalesData[Year]=$B$6))*(($C$6="All")+(SalesData[Quarter]=$C$6))*(($D$6="All")+(SalesData[Month]=$D$6))*(($E$6="All")+(SalesData[Region]=$E$6))*(($F$6="All")+(SalesData[Category]=$F$6))*(($H$6="All")+(SalesData[Product]=$H$6))*SalesData[Revenue]) -> 873158.79 | C84: =SUMPRODUCT((SalesData[Salesperson]=$A$84)*(($B$6="All")+(SalesData[Year]=$B$6))*(($C$6="All")+(SalesData[Quarter]=$C$6))*(($D$6="All")+(SalesData[Month]=$D$6))*(($E$6="All")+(SalesData[Region]=$E$6))*(($F$6="All")+(SalesData[Category]=$F$6))*(($H$6="All")+(SalesData[Product]=$H$6))*((SalesData[Units]<>0))) -> 32 | D84: =SUMPRODUCT((SalesData[Salesperson]=$A$84)*(($B$6="All")+(SalesData[Year]=$B$6))*(($C$6="All")+(SalesData[Quarter]=$C$6))*(($D$6="All")+(SalesData[Month]=$D$6))*(($E$6="All")+(SalesData[Region]=$E$6))*(($F$6="All")+(SalesData[Category]=$F$6))*(($H$6="All")+(SalesData[Product]=$H$6))*SalesData[Units]) -> 710 | E84: =IFERROR(B84/SUM($B$84:$B$89),0) -> 0.17768089 | F84: =B84*Dashboard!$AB$2 -> 873158.79
A85: Sara Ali | B85: =SUMPRODUCT((SalesData[Salesperson]=$A$85)*(($B$6="All")+(SalesData[Year]=$B$6))*(($C$6="All")+(SalesData[Quarter]=$C$6))*(($D$6="All")+(SalesData[Month]=$D$6))*(($E$6="All")+(SalesData[Region]=$E$6))*(($F$6="All")+(SalesData[Category]=$F$6))*(($H$6="All")+(SalesData[Product]=$H$6))*SalesData[Revenue]) -> 677603.15 | C85: =SUMPRODUCT((SalesData[Salesperson]=$A$85)*(($B$6="All")+(SalesData[Year]=$B$6))*(($C$6="All")+(SalesData[Quarter]=$C$6))*(($D$6="All")+(SalesData[Month]=$D$6))*(($E$6="All")+(SalesData[Region]=$E$6))*(($F$6="All")+(SalesData[Category]=$F$6))*(($H$6="All")+(SalesData[Product]=$H$6))*((SalesData[Units]<>0))) -> 25 | D85: =SUMPRODUCT((SalesData[Salesperson]=$A$85)*(($B$6="All")+(SalesData[Year]=$B$6))*(($C$6="All")+(SalesData[Quarter]=$C$6))*(($D$6="All")+(SalesData[Month]=$D$6))*(($E$6="All")+(SalesData[Region]=$E$6))*(($F$6="All")+(SalesData[Category]=$F$6))*(($H$6="All")+(SalesData[Product]=$H$6))*SalesData[Units]) -> 509 | E85: =IFERROR(B85/SUM($B$84:$B$89),0) -> 0.13788687 | F85: =B85*Dashboard!$AB$2 -> 677603.15
A86: Omar Mostafa | B86: =SUMPRODUCT((SalesData[Salesperson]=$A$86)*(($B$6="All")+(SalesData[Year]=$B$6))*(($C$6="All")+(SalesData[Quarter]=$C$6))*(($D$6="All")+(SalesData[Month]=$D$6))*(($E$6="All")+(SalesData[Region]=$E$6))*(($F$6="All")+(SalesData[Category]=$F$6))*(($H$6="All")+(SalesData[Product]=$H$6))*SalesData[Revenue]) -> 635295.81 | C86: =SUMPRODUCT((SalesData[Salesperson]=$A$86)*(($B$6="All")+(SalesData[Year]=$B$6))*(($C$6="All")+(SalesData[Quarter]=$C$6))*(($D$6="All")+(SalesData[Month]=$D$6))*(($E$6="All")+(SalesData[Region]=$E$6))*(($F$6="All")+(SalesData[Category]=$F$6))*(($H$6="All")+(SalesData[Product]=$H$6))*((SalesData[Units]<>0))) -> 30 | D86: =SUMPRODUCT((SalesData[Salesperson]=$A$86)*(($B$6="All")+(SalesData[Year]=$B$6))*(($C$6="All")+(SalesData[Quarter]=$C$6))*(($D$6="All")+(SalesData[Month]=$D$6))*(($E$6="All")+(SalesData[Region]=$E$6))*(($F$6="All")+(SalesData[Category]=$F$6))*(($H$6="All")+(SalesData[Product]=$H$6))*SalesData[Units]) -> 645 | E86: =IFERROR(B86/SUM($B$84:$B$89),0) -> 0.12927766 | F86: =B86*Dashboard!$AB$2 -> 635295.81
A87: Nour Ibrahim | B87: =SUMPRODUCT((SalesData[Salesperson]=$A$87)*(($B$6="All")+(SalesData[Year]=$B$6))*(($C$6="All")+(SalesData[Quarter]=$C$6))*(($D$6="All")+(SalesData[Month]=$D$6))*(($E$6="All")+(SalesData[Region]=$E$6))*(($F$6="All")+(SalesData[Category]=$F$6))*(($H$6="All")+(SalesData[Product]=$H$6))*SalesData[Revenue]) -> 631248.95 | C87: =SUMPRODUCT((SalesData[Salesperson]=$A$87)*(($B$6="All")+(SalesData[Year]=$B$6))*(($C$6="All")+(SalesData[Quarter]=$C$6))*(($D$6="All")+(SalesData[Month]=$D$6))*(($E$6="All")+(SalesData[Region]=$E$6))*(($F$6="All")+(SalesData[Category]=$F$6))*(($H$6="All")+(SalesData[Product]=$H$6))*((SalesData[Units]<>0))) -> 24 | D87: =SUMPRODUCT((SalesData[Salesperson]=$A$87)*(($B$6="All")+(SalesData[Year]=$B$6))*(($C$6="All")+(SalesData[Quarter]=$C$6))*(($D$6="All")+(SalesData[Month]=$D$6))*(($E$6="All")+(SalesData[Region]=$E$6))*(($F$6="All")+(SalesData[Category]=$F$6))*(($H$6="All")+(SalesData[Product]=$H$6))*SalesData[Units]) -> 499 | E87: =IFERROR(B87/SUM($B$84:$B$89),0) -> 0.12845416 | F87: =B87*Dashboard!$AB$2 -> 631248.95
A88: Khaled Youssef | B88: =SUMPRODUCT((SalesData[Salesperson]=$A$88)*(($B$6="All")+(SalesData[Year]=$B$6))*(($C$6="All")+(SalesData[Quarter]=$C$6))*(($D$6="All")+(SalesData[Month]=$D$6))*(($E$6="All")+(SalesData[Region]=$E$6))*(($F$6="All")+(SalesData[Category]=$F$6))*(($H$6="All")+(SalesData[Product]=$H$6))*SalesData[Revenue]) -> 761218.98 | C88: =SUMPRODUCT((SalesData[Salesperson]=$A$88)*(($B$6="All")+(SalesData[Year]=$B$6))*(($C$6="All")+(SalesData[Quarter]=$C$6))*(($D$6="All")+(SalesData[Month]=$D$6))*(($E$6="All")+(SalesData[Region]=$E$6))*(($F$6="All")+(SalesData[Category]=$F$6))*(($H$6="All")+(SalesData[Product]=$H$6))*((SalesData[Units]<>0))) -> 26 | D88: =SUMPRODUCT((SalesData[Salesperson]=$A$88)*(($B$6="All")+(SalesData[Year]=$B$6))*(($C$6="All")+(SalesData[Quarter]=$C$6))*(($D$6="All")+(SalesData[Month]=$D$6))*(($E$6="All")+(SalesData[Region]=$E$6))*(($F$6="All")+(SalesData[Category]=$F$6))*(($H$6="All")+(SalesData[Product]=$H$6))*SalesData[Units]) -> 547 | E88: =IFERROR(B88/SUM($B$84:$B$89),0) -> 0.15490203 | F88: =B88*Dashboard!$AB$2 -> 761218.98
A89: Mona Adel | B89: =SUMPRODUCT((SalesData[Salesperson]=$A$89)*(($B$6="All")+(SalesData[Year]=$B$6))*(($C$6="All")+(SalesData[Quarter]=$C$6))*(($D$6="All")+(SalesData[Month]=$D$6))*(($E$6="All")+(SalesData[Region]=$E$6))*(($F$6="All")+(SalesData[Category]=$F$6))*(($H$6="All")+(SalesData[Product]=$H$6))*SalesData[Revenue]) -> 1335670.6 | C89: =SUMPRODUCT((SalesData[Salesperson]=$A$89)*(($B$6="All")+(SalesData[Year]=$B$6))*(($C$6="All")+(SalesData[Quarter]=$C$6))*(($D$6="All")+(SalesData[Month]=$D$6))*(($E$6="All")+(SalesData[Region]=$E$6))*(($F$6="All")+(SalesData[Category]=$F$6))*(($H$6="All")+(SalesData[Product]=$H$6))*((SalesData[Units]<>0))) -> 43 | D89: =SUMPRODUCT((SalesData[Salesperson]=$A$89)*(($B$6="All")+(SalesData[Year]=$B$6))*(($C$6="All")+(SalesData[Quarter]=$C$6))*(($D$6="All")+(SalesData[Month]=$D$6))*(($E$6="All")+(SalesData[Region]=$E$6))*(($F$6="All")+(SalesData[Category]=$F$6))*(($H$6="All")+(SalesData[Product]=$H$6))*SalesData[Units]) -> 921 | E89: =IFERROR(B89/SUM($B$84:$B$89),0) -> 0.27179839 | F89: =B89*Dashboard!$AB$2 -> 1335670.6
A90: TOTAL | B90: =SUM(B84:B89) -> 4914196.3 | F90: =SUM(F84:F89) -> 4914196.3
A92: 8 | PRODUCT TOTALS (25 SKUs)
A93: Product | B93: Revenue | C93: Profit | D93: Units | E93: Margin %
A94: Bookshelf | B94: =SUMPRODUCT((SalesData[Product]=$A$94)*(($B$6="All")+(SalesData[Year]=$B$6))*(($C$6="All")+(SalesData[Quarter]=$C$6))*(($D$6="All")+(SalesData[Month]=$D$6))*(($E$6="All")+(SalesData[Region]=$E$6))*(($F$6="All")+(SalesData[Category]=$F$6))*(($G$6="All")+(SalesData[Salesperson]=$G$6))*SalesData[Revenue]) -> 425258.29 | C94: =SUMPRODUCT((SalesData[Product]=$A$94)*(($B$6="All")+(SalesData[Year]=$B$6))*(($C$6="All")+(SalesData[Quarter]=$C$6))*(($D$6="All")+(SalesData[Month]=$D$6))*(($E$6="All")+(SalesData[Region]=$E$6))*(($F$6="All")+(SalesData[Category]=$F$6))*(($G$6="All")+(SalesData[Salesperson]=$G$6))*SalesData[Profit]) -> 161598.15 | D94: =SUMPRODUCT((SalesData[Product]=$A$94)*(($B$6="All")+(SalesData[Year]=$B$6))*(($C$6="All")+(SalesData[Quarter]=$C$6))*(($D$6="All")+(SalesData[Month]=$D$6))*(($E$6="All")+(SalesData[Region]=$E$6))*(($F$6="All")+(SalesData[Category]=$F$6))*(($G$6="All")+(SalesData[Salesperson]=$G$6))*SalesData[Units]) -> 176 | E94: =IFERROR(C94/B94,0) -> 0.38
A95: Coffee | B95: =SUMPRODUCT((SalesData[Product]=$A$95)*(($B$6="All")+(SalesData[Year]=$B$6))*(($C$6="All")+(SalesData[Quarter]=$C$6))*(($D$6="All")+(SalesData[Month]=$D$6))*(($E$6="All")+(SalesData[Region]=$E$6))*(($F$6="All")+(SalesData[Category]=$F$6))*(($G$6="All")+(SalesData[Salesperson]=$G$6))*SalesData[Revenue]) -> 20697.68 | C95: =SUMPRODUCT((SalesData[Product]=$A$95)*(($B$6="All")+(SalesData[Year]=$B$6))*(($C$6="All")+(SalesData[Quarter]=$C$6))*(($D$6="All")+(SalesData[Month]=$D$6))*(($E$6="All")+(SalesData[Region]=$E$6))*(($F$6="All")+(SalesData[Category]=$F$6))*(($G$6="All")+(SalesData[Salesperson]=$G$6))*SalesData[Profit]) -> 7865.12 | D95: =SUMPRODUCT((SalesData[Product]=$A$95)*(($B$6="All")+(SalesData[Year]=$B$6))*(($C$6="All")+(SalesData[Quarter]=$C$6))*(($D$6="All")+(SalesData[Month]=$D$6))*(($E$6="All")+(SalesData[Region]=$E$6))*(($F$6="All")+(SalesData[Category]=$F$6))*(($G$6="All")+(SalesData[Salesperson]=$G$6))*SalesData[Units]) -> 208 | E95: =IFERROR(C95/B95,0) -> 0.38000008
A96: Cooking Oil | B96: =SUMPRODUCT((SalesData[Product]=$A$96)*(($B$6="All")+(SalesData[Year]=$B$6))*(($C$6="All")+(SalesData[Quarter]=$C$6))*(($D$6="All")+(SalesData[Month]=$D$6))*(($E$6="All")+(SalesData[Region]=$E$6))*(($F$6="All")+(SalesData[Category]=$F$6))*(($G$6="All")+(SalesData[Salesperson]=$G$6))*SalesData[Revenue]) -> 13501.26 | C96: =SUMPRODUCT((SalesData[Product]=$A$96)*(($B$6="All")+(SalesData[Year]=$B$6))*(($C$6="All")+(SalesData[Quarter]=$C$6))*(($D$6="All")+(SalesData[Month]=$D$6))*(($E$6="All")+(SalesData[Region]=$E$6))*(($F$6="All")+(SalesData[Category]=$F$6))*(($G$6="All")+(SalesData[Salesperson]=$G$6))*SalesData[Profit]) -> 5130.49 | D96: =SUMPRODUCT((SalesData[Product]=$A$96)*(($B$6="All")+(SalesData[Year]=$B$6))*(($C$6="All")+(SalesData[Quarter]=$C$6))*(($D$6="All")+(SalesData[Month]=$D$6))*(($E$6="All")+(SalesData[Region]=$E$6))*(($F$6="All")+(SalesData[Category]=$F$6))*(($G$6="All")+(SalesData[Salesperson]=$G$6))*SalesData[Units]) -> 162 | E96: =IFERROR(C96/B96,0) -> 0.38000083
A97: Desk | B97: =SUMPRODUCT((SalesData[Product]=$A$97)*(($B$6="All")+(SalesData[Year]=$B$6))*(($C$6="All")+(SalesData[Quarter]=$C$6))*(($D$6="All")+(SalesData[Month]=$D$6))*(($E$6="All")+(SalesData[Region]=$E$6))*(($F$6="All")+(SalesData[Category]=$F$6))*(($G$6="All")+(SalesData[Salesperson]=$G$6))*SalesData[Revenue]) -> 548078.28 | C97: =SUMPRODUCT((SalesData[Product]=$A$97)*(($B$6="All")+(SalesData[Year]=$B$6))*(($C$6="All")+(SalesData[Quarter]=$C$6))*(($D$6="All")+(SalesData[Month]=$D$6))*(($E$6="All")+(SalesData[Region]=$E$6))*(($F$6="All")+(SalesData[Category]=$F$6))*(($G$6="All")+(SalesData[Salesperson]=$G$6))*SalesData[Profit]) -> 208269.75 | D97: =SUMPRODUCT((SalesData[Product]=$A$97)*(($B$6="All")+(SalesData[Year]=$B$6))*(($C$6="All")+(SalesData[Quarter]=$C$6))*(($D$6="All")+(SalesData[Month]=$D$6))*(($E$6="All")+(SalesData[Region]=$E$6))*(($F$6="All")+(SalesData[Category]=$F$6))*(($G$6="All")+(SalesData[Salesperson]=$G$6))*SalesData[Units]) -> 185 | E97: =IFERROR(C97/B97,0) -> 0.38000001
A98: Dumbbell Set | B98: =SUMPRODUCT((SalesData[Product]=$A$98)*(($B$6="All")+(SalesData[Year]=$B$6))*(($C$6="All")+(SalesData[Quarter]=$C$6))*(($D$6="All")+(SalesData[Month]=$D$6))*(($E$6="All")+(SalesData[Region]=$E$6))*(($F$6="All")+(SalesData[Category]=$F$6))*(($G$6="All")+(SalesData[Salesperson]=$G$6))*SalesData[Revenue]) -> 28937.8 | C98: =SUMPRODUCT((SalesData[Product]=$A$98)*(($B$6="All")+(SalesData[Year]=$B$6))*(($C$6="All")+(SalesData[Quarter]=$C$6))*(($D$6="All")+(SalesData[Month]=$D$6))*(($E$6="All")+(SalesData[Region]=$E$6))*(($F$6="All")+(SalesData[Category]=$F$6))*(($G$6="All")+(SalesData[Salesperson]=$G$6))*SalesData[Profit]) -> 10996.36 | D98: =SUMPRODUCT((SalesData[Product]=$A$98)*(($B$6="All")+(SalesData[Year]=$B$6))*(($C$6="All")+(SalesData[Quarter]=$C$6))*(($D$6="All")+(SalesData[Month]=$D$6))*(($E$6="All")+(SalesData[Region]=$E$6))*(($F$6="All")+(SalesData[Category]=$F$6))*(($G$6="All")+(SalesData[Salesperson]=$G$6))*SalesData[Units]) -> 104 | E98: =IFERROR(C98/B98,0) -> 0.37999986
A99: Floor Lamp | B99: =SUMPRODUCT((SalesData[Product]=$A$99)*(($B$6="All")+(SalesData[Year]=$B$6))*(($C$6="All")+(SalesData[Quarter]=$C$6))*(($D$6="All")+(SalesData[Month]=$D$6))*(($E$6="All")+(SalesData[Region]=$E$6))*(($F$6="All")+(SalesData[Category]=$F$6))*(($G$6="All")+(SalesData[Salesperson]=$G$6))*SalesData[Revenue]) -> 123282.81 | C99: =SUMPRODUCT((SalesData[Product]=$A$99)*(($B$6="All")+(SalesData[Year]=$B$6))*(($C$6="All")+(SalesData[Quarter]=$C$6))*(($D$6="All")+(SalesData[Month]=$D$6))*(($E$6="All")+(SalesData[Region]=$E$6))*(($F$6="All")+(SalesData[Category]=$F$6))*(($G$6="All")+(SalesData[Salesperson]=$G$6))*SalesData[Profit]) -> 46847.47 | D99: =SUMPRODUCT((SalesData[Product]=$A$99)*(($B$6="All")+(SalesData[Year]=$B$6))*(($C$6="All")+(SalesData[Quarter]=$C$6))*(($D$6="All")+(SalesData[Month]=$D$6))*(($E$6="All")+(SalesData[Region]=$E$6))*(($F$6="All")+(SalesData[Category]=$F$6))*(($G$6="All")+(SalesData[Salesperson]=$G$6))*SalesData[Units]) -> 54 | E99: =IFERROR(C99/B99,0) -> 0.38000002
A100: Football | B100: =SUMPRODUCT((SalesData[Product]=$A$100)*(($B$6="All")+(SalesData[Year]=$B$6))*(($C$6="All")+(SalesData[Quarter]=$C$6))*(($D$6="All")+(SalesData[Month]=$D$6))*(($E$6="All")+(SalesData[Region]=$E$6))*(($F$6="All")+(SalesData[Category]=$F$6))*(($G$6="All")+(SalesData[Salesperson]=$G$6))*SalesData[Revenue]) -> 18173.06 | C100: =SUMPRODUCT((SalesData[Product]=$A$100)*(($B$6="All")+(SalesData[Year]=$B$6))*(($C$6="All")+(SalesData[Quarter]=$C$6))*(($D$6="All")+(SalesData[Month]=$D$6))*(($E$6="All")+(SalesData[Region]=$E$6))*(($F$6="All")+(SalesData[Category]=$F$6))*(($G$6="All")+(SalesData[Salesperson]=$G$6))*SalesData[Profit]) -> 6905.76 | D100: =SUMPRODUCT((SalesData[Product]=$A$100)*(($B$6="All")+(SalesData[Year]=$B$6))*(($C$6="All")+(SalesData[Quarter]=$C$6))*(($D$6="All")+(SalesData[Month]=$D$6))*(($E$6="All")+(SalesData[Region]=$E$6))*(($F$6="All")+(SalesData[Category]=$F$6))*(($G$6="All")+(SalesData[Salesperson]=$G$6))*SalesData[Units]) -> 72 | E100: =IFERROR(C100/B100,0) -> 0.37999985
A101: Headset | B101: =SUMPRODUCT((SalesData[Product]=$A$101)*(($B$6="All")+(SalesData[Year]=$B$6))*(($C$6="All")+(SalesData[Quarter]=$C$6))*(($D$6="All")+(SalesData[Month]=$D$6))*(($E$6="All")+(SalesData[Region]=$E$6))*(($F$6="All")+(SalesData[Category]=$F$6))*(($G$6="All")+(SalesData[Salesperson]=$G$6))*SalesData[Revenue]) -> 759688.02 | C101: =SUMPRODUCT((SalesData[Product]=$A$101)*(($B$6="All")+(SalesData[Year]=$B$6))*(($C$6="All")+(SalesData[Quarter]=$C$6))*(($D$6="All")+(SalesData[Month]=$D$6))*(($E$6="All")+(SalesData[Region]=$E$6))*(($F$6="All")+(SalesData[Category]=$F$6))*(($G$6="All")+(SalesData[Salesperson]=$G$6))*SalesData[Profit]) -> 288681.45 | D101: =SUMPRODUCT((SalesData[Product]=$A$101)*(($B$6="All")+(SalesData[Year]=$B$6))*(($C$6="All")+(SalesData[Quarter]=$C$6))*(($D$6="All")+(SalesData[Month]=$D$6))*(($E$6="All")+(SalesData[Region]=$E$6))*(($F$6="All")+(SalesData[Category]=$F$6))*(($G$6="All")+(SalesData[Salesperson]=$G$6))*SalesData[Units]) -> 187 | E101: =IFERROR(C101/B101,0) -> 0.38
A102: Jacket | B102: =SUMPRODUCT((SalesData[Product]=$A$102)*(($B$6="All")+(SalesData[Year]=$B$6))*(($C$6="All")+(SalesData[Quarter]=$C$6))*(($D$6="All")+(SalesData[Month]=$D$6))*(($E$6="All")+(SalesData[Region]=$E$6))*(($F$6="All")+(SalesData[Category]=$F$6))*(($G$6="All")+(SalesData[Salesperson]=$G$6))*SalesData[Revenue]) -> 43270.61 | C102: =SUMPRODUCT((SalesData[Product]=$A$102)*(($B$6="All")+(SalesData[Year]=$B$6))*(($C$6="All")+(SalesData[Quarter]=$C$6))*(($D$6="All")+(SalesData[Month]=$D$6))*(($E$6="All")+(SalesData[Region]=$E$6))*(($F$6="All")+(SalesData[Category]=$F$6))*(($G$6="All")+(SalesData[Salesperson]=$G$6))*SalesData[Profit]) -> 16442.83 | D102: =SUMPRODUCT((SalesData[Product]=$A$102)*(($B$6="All")+(SalesData[Year]=$B$6))*(($C$6="All")+(SalesData[Quarter]=$C$6))*(($D$6="All")+(SalesData[Month]=$D$6))*(($E$6="All")+(SalesData[Region]=$E$6))*(($F$6="All")+(SalesData[Category]=$F$6))*(($G$6="All")+(SalesData[Salesperson]=$G$6))*SalesData[Units]) -> 137 | E102: =IFERROR(C102/B102,0) -> 0.37999996
A103: Jeans | B103: =SUMPRODUCT((SalesData[Product]=$A$103)*(($B$6="All")+(SalesData[Year]=$B$6))*(($C$6="All")+(SalesData[Quarter]=$C$6))*(($D$6="All")+(SalesData[Month]=$D$6))*(($E$6="All")+(SalesData[Region]=$E$6))*(($F$6="All")+(SalesData[Category]=$F$6))*(($G$6="All")+(SalesData[Salesperson]=$G$6))*SalesData[Revenue]) -> 38812.11 | C103: =SUMPRODUCT((SalesData[Product]=$A$103)*(($B$6="All")+(SalesData[Year]=$B$6))*(($C$6="All")+(SalesData[Quarter]=$C$6))*(($D$6="All")+(SalesData[Month]=$D$6))*(($E$6="All")+(SalesData[Region]=$E$6))*(($F$6="All")+(SalesData[Category]=$F$6))*(($G$6="All")+(SalesData[Salesperson]=$G$6))*SalesData[Profit]) -> 14748.62 | D103: =SUMPRODUCT((SalesData[Product]=$A$103)*(($B$6="All")+(SalesData[Year]=$B$6))*(($C$6="All")+(SalesData[Quarter]=$C$6))*(($D$6="All")+(SalesData[Month]=$D$6))*(($E$6="All")+(SalesData[Region]=$E$6))*(($F$6="All")+(SalesData[Category]=$F$6))*(($G$6="All")+(SalesData[Salesperson]=$G$6))*SalesData[Units]) -> 138 | E103: =IFERROR(C103/B103,0) -> 0.38000047
A104: Laptop | B104: =SUMPRODUCT((SalesData[Product]=$A$104)*(($B$6="All")+(SalesData[Year]=$B$6))*(($C$6="All")+(SalesData[Quarter]=$C$6))*(($D$6="All")+(SalesData[Month]=$D$6))*(($E$6="All")+(SalesData[Region]=$E$6))*(($F$6="All")+(SalesData[Category]=$F$6))*(($G$6="All")+(SalesData[Salesperson]=$G$6))*SalesData[Revenue]) -> 360465.92 | C104: =SUMPRODUCT((SalesData[Product]=$A$104)*(($B$6="All")+(SalesData[Year]=$B$6))*(($C$6="All")+(SalesData[Quarter]=$C$6))*(($D$6="All")+(SalesData[Month]=$D$6))*(($E$6="All")+(SalesData[Region]=$E$6))*(($F$6="All")+(SalesData[Category]=$F$6))*(($G$6="All")+(SalesData[Salesperson]=$G$6))*SalesData[Profit]) -> 136977.05 | D104: =SUMPRODUCT((SalesData[Product]=$A$104)*(($B$6="All")+(SalesData[Year]=$B$6))*(($C$6="All")+(SalesData[Quarter]=$C$6))*(($D$6="All")+(SalesData[Month]=$D$6))*(($E$6="All")+(SalesData[Region]=$E$6))*(($F$6="All")+(SalesData[Category]=$F$6))*(($G$6="All")+(SalesData[Salesperson]=$G$6))*SalesData[Units]) -> 108 | E104: =IFERROR(C104/B104,0) -> 0.38
A105: Monitor | B105: =SUMPRODUCT((SalesData[Product]=$A$105)*(($B$6="All")+(SalesData[Year]=$B$6))*(($C$6="All")+(SalesData[Quarter]=$C$6))*(($D$6="All")+(SalesData[Month]=$D$6))*(($E$6="All")+(SalesData[Region]=$E$6))*(($F$6="All")+(SalesData[Category]=$F$6))*(($G$6="All")+(SalesData[Salesperson]=$G$6))*SalesData[Revenue]) -> 435057.77 | C105: =SUMPRODUCT((SalesData[Product]=$A$105)*(($B$6="All")+(SalesData[Year]=$B$6))*(($C$6="All")+(SalesData[Quarter]=$C$6))*(($D$6="All")+(SalesData[Month]=$D$6))*(($E$6="All")+(SalesData[Region]=$E$6))*(($F$6="All")+(SalesData[Category]=$F$6))*(($G$6="All")+(SalesData[Salesperson]=$G$6))*SalesData[Profit]) -> 165321.95 | D105: =SUMPRODUCT((SalesData[Product]=$A$105)*(($B$6="All")+(SalesData[Year]=$B$6))*(($C$6="All")+(SalesData[Quarter]=$C$6))*(($D$6="All")+(SalesData[Month]=$D$6))*(($E$6="All")+(SalesData[Region]=$E$6))*(($F$6="All")+(SalesData[Category]=$F$6))*(($G$6="All")+(SalesData[Salesperson]=$G$6))*SalesData[Units]) -> 132 | E105: =IFERROR(C105/B105,0) -> 0.37999999
A106: Office Chair | B106: =SUMPRODUCT((SalesData[Product]=$A$106)*(($B$6="All")+(SalesData[Year]=$B$6))*(($C$6="All")+(SalesData[Quarter]=$C$6))*(($D$6="All")+(SalesData[Month]=$D$6))*(($E$6="All")+(SalesData[Region]=$E$6))*(($F$6="All")+(SalesData[Category]=$F$6))*(($G$6="All")+(SalesData[Salesperson]=$G$6))*SalesData[Revenue]) -> 216559.28 | C106: =SUMPRODUCT((SalesData[Product]=$A$106)*(($B$6="All")+(SalesData[Year]=$B$6))*(($C$6="All")+(SalesData[Quarter]=$C$6))*(($D$6="All")+(SalesData[Month]=$D$6))*(($E$6="All")+(SalesData[Region]=$E$6))*(($F$6="All")+(SalesData[Category]=$F$6))*(($G$6="All")+(SalesData[Salesperson]=$G$6))*SalesData[Profit]) -> 82292.53 | D106: =SUMPRODUCT((SalesData[Product]=$A$106)*(($B$6="All")+(SalesData[Year]=$B$6))*(($C$6="All")+(SalesData[Quarter]=$C$6))*(($D$6="All")+(SalesData[Month]=$D$6))*(($E$6="All")+(SalesData[Region]=$E$6))*(($F$6="All")+(SalesData[Category]=$F$6))*(($G$6="All")+(SalesData[Salesperson]=$G$6))*SalesData[Units]) -> 79 | E106: =IFERROR(C106/B106,0) -> 0.38000002
A107: Rice | B107: =SUMPRODUCT((SalesData[Product]=$A$107)*(($B$6="All")+(SalesData[Year]=$B$6))*(($C$6="All")+(SalesData[Quarter]=$C$6))*(($D$6="All")+(SalesData[Month]=$D$6))*(($E$6="All")+(SalesData[Region]=$E$6))*(($F$6="All")+(SalesData[Category]=$F$6))*(($G$6="All")+(SalesData[Salesperson]=$G$6))*SalesData[Revenue]) -> 12560.67 | C107: =SUMPRODUCT((SalesData[Product]=$A$107)*(($B$6="All")+(SalesData[Year]=$B$6))*(($C$6="All")+(SalesData[Quarter]=$C$6))*(($D$6="All")+(SalesData[Month]=$D$6))*(($E$6="All")+(SalesData[Region]=$E$6))*(($F$6="All")+(SalesData[Category]=$F$6))*(($G$6="All")+(SalesData[Salesperson]=$G$6))*SalesData[Profit]) -> 4773.05 | D107: =SUMPRODUCT((SalesData[Product]=$A$107)*(($B$6="All")+(SalesData[Year]=$B$6))*(($C$6="All")+(SalesData[Quarter]=$C$6))*(($D$6="All")+(SalesData[Month]=$D$6))*(($E$6="All")+(SalesData[Region]=$E$6))*(($F$6="All")+(SalesData[Category]=$F$6))*(($G$6="All")+(SalesData[Salesperson]=$G$6))*SalesData[Units]) -> 175 | E107: =IFERROR(C107/B107,0) -> 0.37999963
A108: Smartphone | B108: =SUMPRODUCT((SalesData[Product]=$A$108)*(($B$6="All")+(SalesData[Year]=$B$6))*(($C$6="All")+(SalesData[Quarter]=$C$6))*(($D$6="All")+(SalesData[Month]=$D$6))*(($E$6="All")+(SalesData[Region]=$E$6))*(($F$6="All")+(SalesData[Category]=$F$6))*(($G$6="All")+(SalesData[Salesperson]=$G$6))*SalesData[Revenue]) -> 471256.17 | C108: =SUMPRODUCT((SalesData[Product]=$A$108)*(($B$6="All")+(SalesData[Year]=$B$6))*(($C$6="All")+(SalesData[Quarter]=$C$6))*(($D$6="All")+(SalesData[Month]=$D$6))*(($E$6="All")+(SalesData[Region]=$E$6))*(($F$6="All")+(SalesData[Category]=$F$6))*(($G$6="All")+(SalesData[Salesperson]=$G$6))*SalesData[Profit]) -> 179077.34 | D108: =SUMPRODUCT((SalesData[Product]=$A$108)*(($B$6="All")+(SalesData[Year]=$B$6))*(($C$6="All")+(SalesData[Quarter]=$C$6))*(($D$6="All")+(SalesData[Month]=$D$6))*(($E$6="All")+(SalesData[Region]=$E$6))*(($F$6="All")+(SalesData[Category]=$F$6))*(($G$6="All")+(SalesData[Salesperson]=$G$6))*SalesData[Units]) -> 177 | E108: =IFERROR(C108/B108,0) -> 0.37999999
A109: Sneakers | B109: =SUMPRODUCT((SalesData[Product]=$A$109)*(($B$6="All")+(SalesData[Year]=$B$6))*(($C$6="All")+(SalesData[Quarter]=$C$6))*(($D$6="All")+(SalesData[Month]=$D$6))*(($E$6="All")+(SalesData[Region]=$E$6))*(($F$6="All")+(SalesData[Category]=$F$6))*(($G$6="All")+(SalesData[Salesperson]=$G$6))*SalesData[Revenue]) -> 67267.45 | C109: =SUMPRODUCT((SalesData[Product]=$A$109)*(($B$6="All")+(SalesData[Year]=$B$6))*(($C$6="All")+(SalesData[Quarter]=$C$6))*(($D$6="All")+(SalesData[Month]=$D$6))*(($E$6="All")+(SalesData[Region]=$E$6))*(($F$6="All")+(SalesData[Category]=$F$6))*(($G$6="All")+(SalesData[Salesperson]=$G$6))*SalesData[Profit]) -> 25561.61 | D109: =SUMPRODUCT((SalesData[Product]=$A$109)*(($B$6="All")+(SalesData[Year]=$B$6))*(($C$6="All")+(SalesData[Quarter]=$C$6))*(($D$6="All")+(SalesData[Month]=$D$6))*(($E$6="All")+(SalesData[Region]=$E$6))*(($F$6="All")+(SalesData[Category]=$F$6))*(($G$6="All")+(SalesData[Salesperson]=$G$6))*SalesData[Units]) -> 206 | E109: =IFERROR(C109/B109,0) -> 0.37999969
A110: Sofa | B110: =SUMPRODUCT((SalesData[Product]=$A$110)*(($B$6="All")+(SalesData[Year]=$B$6))*(($C$6="All")+(SalesData[Quarter]=$C$6))*(($D$6="All")+(SalesData[Month]=$D$6))*(($E$6="All")+(SalesData[Region]=$E$6))*(($F$6="All")+(SalesData[Category]=$F$6))*(($G$6="All")+(SalesData[Salesperson]=$G$6))*SalesData[Revenue]) -> 691271.67 | C110: =SUMPRODUCT((SalesData[Product]=$A$110)*(($B$6="All")+(SalesData[Year]=$B$6))*(($C$6="All")+(SalesData[Quarter]=$C$6))*(($D$6="All")+(SalesData[Month]=$D$6))*(($E$6="All")+(SalesData[Region]=$E$6))*(($F$6="All")+(SalesData[Category]=$F$6))*(($G$6="All")+(SalesData[Salesperson]=$G$6))*SalesData[Profit]) -> 262683.24 | D110: =SUMPRODUCT((SalesData[Product]=$A$110)*(($B$6="All")+(SalesData[Year]=$B$6))*(($C$6="All")+(SalesData[Quarter]=$C$6))*(($D$6="All")+(SalesData[Month]=$D$6))*(($E$6="All")+(SalesData[Region]=$E$6))*(($F$6="All")+(SalesData[Category]=$F$6))*(($G$6="All")+(SalesData[Salesperson]=$G$6))*SalesData[Units]) -> 244 | E110: =IFERROR(C110/B110,0) -> 0.38000001
...
